{"59b6529de3567a0001d9bed7": "david.lascelles@multiressource.qc.ca", "59b6510ae3567a0001d9be79": "guillermosorianoo@gmail.com", "59b652470edf79000135dab2": "cayetano.benavent@geographica.gs", "59b652410edf79000135dab0": "coyotegreen@gmail.com", "59b65576faeeee0001d1e708": "tommasi@geomind.it", "59b655bbfaeeee0001d1e717": "shadowalice@hotmail.co.th", "5a0723fc4d6a430001b265f8": "duncangager1@yahoo.co.uk", "5a0182b29742bf00019b864e": "niesmarc@gmail.com", "59b652b70edf79000135dacb": "alessandra_schintu3@hotmail.com", "59b65469faeeee0001d1e6bd": "pm@freiraumweb.de", "59b653a95a8b5b00013113c0": "carlossimental81@gmail.com", "59d501fcc33c720001b2b835": "EDGAR.AA@AMIDCONSULTORIA.COM", "59fcb7f1144ad1000197c4f8": "danieletognozzi@gmail.com", "59b653675a8b5b00013113b0": "a338363a@gmail.com", "59b652ae0edf79000135dac9": "christelle.croyet@atelierurbain.net", "5a1af0c37230f90001c1132b": "ischl25osm@trash-mail.com", "59b6516ffaeeee0001d1e5eb": "hdg@p-good.nl", "5a2078b45ad3140001b9d101": "vegaijurco@hotmail.com", "59bf22a2343ef100010ce7e5": "h.herzig@besonet.ch", "59b65507e3567a0001d9bf7e": "enigma.muc@gmail.com", "59fb0239144ad1000197c4c1": "phuongimc411@gmail.com", "5a25c5a05bf58500012bee99": "tina.welt@gmx.de", "59b6556ffaeeee0001d1e706": "jan.smitsman@gmail.com", "59b65176faeeee0001d1e5ec": "marosas@ciencias.unam.mx", "59b6554c5a8b5b000131142e": "ata.tara@rmit.edu.au", "59b652b55a8b5b000131137e": "fpruneau@outlook.fr", "59b65108e3567a0001d9be78": "dallas.cotterell@cushwake.com", "59b65486faeeee0001d1e6c9": "koesters@uhv71.de", "59b6529e5a8b5b0001311374": "cvetlicni11@gmail.com", "59b653f10edf79000135db3a": "john_spencer@unc.edu", "59b65431e3567a0001d9bf49": "Falk-Zedler@gmx.de", "59b6542a0edf79000135db46": "david.eagle@1spatial.com", "59e20d1cb8125f0001376843": "christoph.schormair@arcor.de", "59b6516cfaeeee0001d1e5ea": "olizzs@yahoo.de", "59b6533c0edf79000135dafc": "jinlin@mail.ndhu.edu.tw", "59d4f48782f2000001f71407": "pwbanta@gmail.com", "59b650f00edf79000135da60": "petr@tictactrip.eu", "59b65572e782050001d6716a": "olegaarde@gmail.com", "59b652b4faeeee0001d1e641": "jjoubert@bunbury.wa.gov.au", "59b653d2faeeee0001d1e693": "info@eidatec.de", "59b65251faeeee0001d1e621": "angel.chelaru@parametric.support", "59b653ece3567a0001d9bf35": "cagito@naver.com", "59b654860edf79000135db67": "jose.soares@telenet.be", "59b6528ee3567a0001d9bed1": "estebanh182@hotmail.com", "59b651d5faeeee0001d1e602": "gioantonvelez@gmail.com", "59b655065a8b5b0001311422": "jjones@outlook.cz", "59b652fb5a8b5b0001311391": "kentaro.takahira@gmail.com", "59b651d50edf79000135da99": "Roland.Michel@onlinehome.de", "59b654f7e782050001d6714e": "emhu916@gmail.com", "59b65419e3567a0001d9bf40": "bocsiboti@gmail.com", "59b6527fe3567a0001d9becd": "jreyestorres@gmail.com", "59b6505bdac3350001574f89": "a.fossart@laposte.net", "59b65196e3567a0001d9be95": "jxiao@au.ncs-i.com", "59b6524b0edf79000135dab3": "oom@xs4all.nl", "5a27b136ccafd100012c6948": "lars.udina@porsche-engineering.de", "59b655455a8b5b000131142c": "aib@gevbologna.org", "5a15628af7e6a4000165dfe7": "dorothee.schulz@gmx.de", "59b653890edf79000135db1a": "geyer.erich@gmx.de", "59b6533f0edf79000135dafd": "erquan.zhou@rwth-aachen.de", "59b655c5faeeee0001d1e719": "mabourgault@latelierurbain.com", "59b7f5c7017007000152b075": "vincenzo.cerreta@alice.it", "59b6538f0edf79000135db1b": "b.koehl@kreis-hoexter.de", "59b6520d5a8b5b0001311349": "orcutt989@gmail.com", "59b6520d5a8b5b0001311348": "contact@myroutes.io", "59b6524f0edf79000135dab4": "janboers@gmail.com", "59b653e0e3567a0001d9bf31": "ersin.aksoy76@gmail.com", "5a06c55c4d6a430001b265f2": "pierre.jochems@ruimteenrichting.com", "59b6514a0edf79000135da76": "hannes.schreier@team-red.net", "5a0189e036c1df00016cea4e": "amandus@openrouteservice.org", "59b654d0e782050001d67140": "pedro.camargo@veitchlister.com.au", "59b651a8faeeee0001d1e5f7": "hannelore@yahoo.de", "59b653e7faeeee0001d1e69a": "2mangojuice2@gmail.com", "59b652ef0edf79000135dadf": "spam+openrouteservice@dittberner.it", "59b651cf0edf79000135da98": "stephane.joost@epfl.ch", "59b65528faeeee0001d1e6f4": "alexia-kara@hotmail.fr", "59b653d8e3567a0001d9bf2d": "w.black@barclaycomms.com", "59b651c0faeeee0001d1e5fb": "yevhen.chuhui@gmail.com", "59b6524ce3567a0001d9bec1": "chris.m.franciskovich@osfhealthcare.org", "59b652d15a8b5b0001311386": "mail@benedictzinke.de", "59b6510c0edf79000135da66": "jeeva.d.moorthy@gmail.com", "59b653d45a8b5b00013113ca": "webmaster@navyonline.it", "5a02f252a107160001a5a25f": "zipf@uni-heidelberg.de", "5a1d7282d415c9000195874b": "thomas.moliner60@gmail.com", "59b6511b0edf79000135da69": "bb@benjaminbruecker.de", "5a1b16247230f90001c1132d": "doug.drew@rogers.com", "59b6519ee3567a0001d9be97": "david_copeland1@yahoo.com", "59b653605a8b5b00013113ae": "41050A006@gms.ndhu.edu.tw", "59b653690edf79000135db0f": "vincent.vauchey@iea45.fr", "59b6536a5a8b5b00013113b2": "maurizio.francescon@gmail.com", "59b6520a5a8b5b0001311347": "miljenko.vincek@gmail.com", "59b6526e5a8b5b0001311369": "ololol60@gmail.com", "59b6545c0edf79000135db5b": "Henning.Huenemohr@t-online.de", "59b653eefaeeee0001d1e69d": "nutzenfuerarbeit@gmail.com", "59b652505a8b5b0001311361": "mailbyneeks@protonmail.com", "59b653a00edf79000135db1f": "neimeier@fh-muenster.de", "59ee21d67c22600001ca84d3": "kelly@brpoolsusa.com", "59b655c7e3567a0001d9bfa6": "11Noblea@mail.altrinchamcollege.com", "59f9a651144ad1000197c4a1": "flazzarotto1@alice.it", "59b652e35a8b5b000131138a": "r.a.boer@umcg.nl", "59b652c55a8b5b0001311381": "zamenislineatus@yahoo.it", "59b653b6faeeee0001d1e689": "kay.zobel@hcu-hamburg.de", "59b65305e3567a0001d9bef4": "bhavin.mehta@ecodev.vic.gov.au", "59b81e283f17050001cdcb74": "titovvlad1997@yandex.ru", "59cb92eb39e49a00015a50a2": "xmiquel@nexusgeographics.com", "59b6536e0edf79000135db10": "w.struzyna@web.de", "59b65308e3567a0001d9bef5": "samtondi@gmail.com", "59b652e7faeeee0001d1e651": "mail@sebastian-krebs.com", "59b650e10edf79000135da5d": "joancasabo@hotmail.com", "59b654af0edf79000135db70": "gj.vreeswijk@wxs.nl", "59b654380edf79000135db4b": "daniel.hilpoltsteiner@haw-landshut.de", "59b6541e5a8b5b00013113e0": "alickbrown@outlook.com", "59b65228faeeee0001d1e616": "wahyu4ed@gmail.com", "59b6524a5a8b5b000131135e": "weisse_maske@freenet.de", "59b6524a5a8b5b000131135f": "belugafish@mail.ru", "5a0c6c650b6b330001e54367": "pola.mina@pharos-solutions.de", "59b6521f5a8b5b000131134e": "paulds8@hotmail.com", "59b65101e3567a0001d9be75": "rwhaley@threesquare.org", "59b6516afaeeee0001d1e5e9": "mr.mosch@gmail.com", "59b655b5faeeee0001d1e714": "nick4542@yahoo.com", "59b6551cfaeeee0001d1e6f0": "mf_ttu@yahoo.com", "59b65382e3567a0001d9bf15": "ch.chaitanya94@gmail.com", "59b652655a8b5b0001311368": "marcin.sawiak@gmail.com", "59b653e35a8b5b00013113cd": "chris.nall@uhi.ac.uk", "59b65440e3567a0001d9bf4d": "mail@bjoernschwentker.de", "59b652c40edf79000135dad0": "massimiliano.guarneri@enea.it", "5a06fb2e4d6a430001b265f4": "f24046179@ncku.mail.edu.tw", "59b652d5e3567a0001d9bee5": "ansc@carl-ras.dk", "59b654dce782050001d67145": "kris.loodts@geel.be", "59b652165a8b5b000131134c": "bestymw@hotmail.com", "59b651f1faeeee0001d1e608": "pignocc@tin.it", "59b651cb5a8b5b0001311335": "elin.brudin@sjobo.se", "59fc8d2a5d62150001daf908": "leslie.pfaff@web.de", "59b6552f0edf79000135db84": "martin.thurnher@c3online.at", "59b65466faeeee0001d1e6bb": "mpontious@gmail.com", "59b65589e782050001d6716e": "rodliyahsiti03@gmail.com", "59b65589e782050001d6716d": "john@ctcreativegroup.com", "59b652955a8b5b0001311372": "saalplatz2000@gmail.com", "59b652f5faeeee0001d1e655": "gesine.pohl@bpv-consult.net", "59b650e0dac3350001574f94": "scarselli@gmail.com", "59b65205dac3350001574fd1": "pdc0608@gmail.com", "59ff0cdc144ad1000197c530": "dani.haechl@web.de", "59b651d9dac3350001574fc3": "fcanalella@gmail.com", "59b650b4dac3350001574f91": "cyrille@eii.fr", "59b653710edf79000135db11": "tommy1234227@gmail.com", "59b654205a8b5b00013113e1": "giovannirinaldi_002@fastwebnet.it", "59fdd46874fe4a0001be6898": "arapone@durabond.com", "59b653b70edf79000135db26": "warren.lewington@students.mq.edu.ai", "5a28fe8dd62a6c0001faba04": "tatjana.huebner@schwaben.ihk.de", "59b654a25a8b5b000131140c": "nordsee2000-osm@yahoo.com", "59b6555ae782050001d67165": "amadeu.penzin@gmail.com", "59b654b35a8b5b0001311410": "gerold.ludwig@komobile.at", "59b650be5a8b5b00013112fd": "kta@forium.de", "59b6550f0edf79000135db7f": "nils@schwabe.ws", "59b651adfaeeee0001d1e5f9": "efrainacgo@gmail.com", "59b652aafaeeee0001d1e63e": "michael.swaim@gmail.com", "59b652850edf79000135dac0": "thiagoterto@hotmail.com", "5a041bd71841360001ad5934": "lopez_raq@gva.es", "59f61ab8639a130001929252": "christine.ehrne@gmx.at", "59b65179faeeee0001d1e5ee": "gilberttim09@gmail.com", "59b6542cfaeeee0001d1e6b0": "iman.s1369@gmail.com", "59b652ab5a8b5b000131137b": "pmdscully+tourplanner@gmail.com", "59b6547ae3567a0001d9bf5a": "winfried.boennhoff@smserp.de", "59b650fdfaeeee0001d1e5cc": "maps@porstmann.org", "59b652f9e3567a0001d9beef": "chalky94@hotmail.com", "59b653af0edf79000135db23": "davide@nowhere.it", "59b65508e3567a0001d9bf80": "surajhpatil@gmail.com", "59b652dce3567a0001d9bee6": "thomaseberl@hotmail.com", "59b6538be3567a0001d9bf17": "bmikosdi@gmail.com", "59b651995a8b5b0001311329": "odumat@bee-industries.de", "59b651f45a8b5b0001311341": "me@yokto.net", "59b651cbdac3350001574fc0": "hugo.stappaerts@telenet.be", "59b65543faeeee0001d1e6fc": "serouge@jonction.fr", "59b652260edf79000135daa8": "yusukeso7884@zenrin.co.jp", "59b652f9faeeee0001d1e656": "soegenkgie@gmail.com", "59b652d4faeeee0001d1e64c": "supersbx00@gmail.com", "59b654085a8b5b00013113d8": "mahmoudabdelzaher35@gmail.com", "59b6530ee3567a0001d9bef6": "Ed.symons@nscc.ca", "59b652a6e3567a0001d9beda": "jhoogenboom@bonotraffics.nl", "59d25c1098af3e0001ba1891": "jose@eduardodeboni.com", "59b6509c5a8b5b00013112fb": "hguendra@geonet-mrn.de", "59b651755a8b5b000131131f": "diazsilva.alberto@gmail.com", "59b655d25a8b5b0001311447": "wtint1776@gmail.com", "59b651fd5a8b5b0001311345": "c.demonie@live.be", "59b6520bdac3350001574fd3": "christian.bettendorff@villeesch.lu", "59b6553b5a8b5b000131142a": "hansschollaardt@gmail.com", "59b654f3e782050001d6714c": "rogergodoy@gmail.com", "59b6525cfaeeee0001d1e625": "rajack@uwindsor.ca", "59b6559c5a8b5b000131143d": "djmanser001@gmail.com", "59b654050edf79000135db3f": "orel.tlt@gmail.com", "59b65115e3567a0001d9be7d": "jon.bennison@suez.com", "59b65269faeeee0001d1e62b": "thomas.good@outlook.com", "59b653cffaeeee0001d1e692": "joern.caro@yahoo.de", "59b653d9faeeee0001d1e695": "og1975@ya.ru", "59b6543ae3567a0001d9bf4b": "doopyon@gmail.com", "59b65195dac3350001574fb7": "krisian@onefellswoop.com.au", "59b65347faeeee0001d1e669": "jeremy.r.castle@gmail.com", "59dcf0e5b8125f0001376795": "c-revermann@gmx.de", "59b652680edf79000135dab6": "samuel.mermet@afbiodiversite.fr", "59ec4156ad0b560001855c8b": "notreal@airmail.cc", "5a06faf74d6a430001b265f3": "tucynthia111700@gmail.com", "59b654de0edf79000135db77": "jlopez@tecnocampus.cat", "59b65131faeeee0001d1e5db": "hikrwebsite@gmail.com", "59b6514ddac3350001574fa9": "daniel.sichler@deutschebahn.com", "59b6531e5a8b5b000131139b": "margus.tiru@gmail.com", "59b65444e3567a0001d9bf4e": "oschmidt@netstyle.de", "59ba59c2784abe0001c4b0b8": "claire.l.birnie@gmail.com", "59b6512efaeeee0001d1e5d9": "kofihenaku@yahoo.co.uk", "59b65536e782050001d6715d": "ugo@ecov.fr", "59b65116faeeee0001d1e5d1": "markus.menz@kreis-unna.de", "59b651f0dac3350001574fca": "tatianapotapova777@yandex.ru", "59b654635a8b5b00013113f9": "oliv.marcel@gmail.com", "5a310602d3fd6200016828e9": "tmoliner@bemh.fr", "59b65513faeeee0001d1e6ec": "marcin.wiercioch@okinet.pl", "59ff64a1144ad1000197c534": "w.g.dirks@xmsnet.nl", "59b65532e782050001d6715b": "alexanenkovad@gmail.com", "59b654f7e782050001d6714d": "gemma.tolosa@gmail.com", "59b65243e3567a0001d9bebe": "thor.berglie@gmail.com", "59b6548ee3567a0001d9bf5e": "kevbost@gmail.com", "59b654bfe782050001d6713b": "j.j.vander.kemp@vu.nl", "59b6513e0edf79000135da71": "acct1001@yahoo.com", "59b65449faeeee0001d1e6b4": "info@artderstadt.de", "59c398f86070ca0001f62a0e": "dolfpereboom@gmail.com", "59b65104dac3350001574f9d": "vadim.podgornyh@gmail.com", "59d4c6c5b8125f000137668d": "henschel@raumentwickler.de", "59b655a55a8b5b000131143f": "bas@vaneldonk.com", "59b653d55a8b5b00013113cb": "mathieu.paul@iprospect.com", "59b654e35a8b5b000131141a": "pete@city-farmers.co.uk", "59b6539e0edf79000135db1e": "aleksey.kasianik@gmail.com", "59b655d6e3567a0001d9bfab": "martin.ress.wangen@gmail.com", "59b6528be3567a0001d9bed0": "rowan.langford@summitllc.us", "59b652635a8b5b0001311367": "jdk@midttrafik.dk", "59b65253faeeee0001d1e622": "Christianwagner84@googlemail.com", "59b653280edf79000135daf2": "eugen.hanussek@klst.com", "59b651490edf79000135da75": "francois_lamonerie@msn.com", "5a02cfdede7f9a0001d0c0a6": "wuthichai@buu.ac.th", "59b653aefaeeee0001d1e687": "milagi32@hotmail.com", "59b654efe3567a0001d9bf75": "reso.gabor@gmail.com", "5a044b21e32d8b0001683e22": "g_davidoff@mail.ru", "59b654c8faeeee0001d1e6da": "marwaboulakbech@gmail.com", "59b653f05a8b5b00013113cf": "nerkes@jfcsphilly.org", "59b6541e5a8b5b00013113df": "espinozasebas94@gmail.com", "59b653acfaeeee0001d1e685": "kamioremilia@gmail.com", "59b652b6faeeee0001d1e642": "nuigi5@gmail.com", "59d33c5b1a53ab00014e5c77": "alexis.gumy@pully.ch", "59b65329faeeee0001d1e664": "herbert.twiefel@gmx.de", "59b65263e3567a0001d9bec5": "krogh.rikke@hotmail.com", "59b655a8faeeee0001d1e710": "19901@7733.ru", "59b650e9e3567a0001d9be70": "kitjwatson@gmail.com", "59d26ff26b87dc00013915a7": "paonessafabrizio@gmail.com", "59e9e7b2abb9930001c63e83": "michele.fasolo@gmail.com", "59e090a1713208000170700c": "bruizer@outlook.com", "59b65451e3567a0001d9bf52": "marellano.ace@gmail.com", "59b652850edf79000135dabf": "andrewnoyce@gmail.com", "59b651cedac3350001574fc2": "nemfethi@yahoo.fr", "59b6559ee782050001d67172": "mdhunnooa@gmail.com", "59b6542dfaeeee0001d1e6b1": "manustrok@gmail.com", "59b6551ae782050001d67155": "f.phelep@ellipsa.com", "59b652b30edf79000135daca": "openrouteservice@searchiv.com", "59b655b7e3567a0001d9bfa1": "ms@aranes.de", "59b6537ce3567a0001d9bf12": "aitoruranga@gmail.com", "59b654f4faeeee0001d1e6e7": "maksim.rylov@gmail.com", "59e77483b8125f00013768f7": "victor.mange@hotmail.fr", "59b651da5a8b5b000131133a": "anubhavxsingh@gmail.com", "59b65598faeeee0001d1e70b": "xyt556@gmail.com", "59b6543a0edf79000135db4c": "deshan.r@fidenz.com", "59b651925a8b5b0001311327": "flokmachin@hotmail.fr", "59b653810edf79000135db17": "tom@searbys.co.uk", "59b652cce3567a0001d9bee4": "gseggie@systra.com", "59f434365c524200016c9be2": "shah.nishant@dalmiacement.com", "5a2a14812601b9000181cead": "sk7shatty7@gmail.com", "59b65364e3567a0001d9bf0a": "ng@archimedes-exhibitions.de", "59b6538f5a8b5b00013113bc": "maxence@handytown.fr", "59b651820edf79000135da83": "holothurie.online@yahoo.com", "59b65064e3567a0001d9be6c": "corinna.buhlrich@rwth-aachen.de", "59b653e60edf79000135db37": "gwalker84@gmail.com", "59b653ea0edf79000135db38": "giano76@tiscali.it", "5a04fa7fbe7e1300014d4ca9": "grafpaper@gmail.com", "59b650f5dac3350001574f98": "pascal.ziegler@web.de", "59b6525b0edf79000135dab5": "tom-hasport@gmx.net", "59f04a55b8125f0001376a24": "klaus-peter.hurtig@hotmail.de", "59b651d25a8b5b0001311337": "evgen.solodilov@gmail.com", "59b652bd0edf79000135dacc": "alexxsandrosampaio@gmail.com", "59f29329b8125f0001376a6c": "mpakzadm@yahoo.com", "59b651285a8b5b000131130e": "waynelukwt@gmail.com", "59f294ad2ada0e000139aed7": "364430846@qq.com", "59b65373faeeee0001d1e671": "phoward@burditt.com", "59b650aadac3350001574f8f": "peter@multisoft.hu", "59b652990edf79000135dac4": "Stephan.Schneijderberg@bam.com", "59b6554ee3567a0001d9bf8e": "bastian.joe@tcs.com", "59f0776ab8125f0001376a31": "shermina@njsig.org", "59b655125a8b5b0001311424": "bcquote2016@null.net", "59b653325a8b5b00013113a3": "oetjens@geo-net.de", "59b653600edf79000135db0c": "zsx422660@gmail.com", "59b6522f0edf79000135daab": "steffen.albrecht@acando.de", "59b653e6faeeee0001d1e699": "mrc_mm_sp@web.de", "59b6556e0edf79000135db91": "U.Jacke@stud.uni-heidelberg.de", "59b654c5faeeee0001d1e6d9": "otabcr@gmail.com", "59b65315faeeee0001d1e65f": "musamokhtar2@gmail.com", "5a0ddaaccd9a9900013d382c": "nele.jannes@gmail.com", "59b651d8faeeee0001d1e603": "mohammad.azadi@yahoo.com", "59b653ca0edf79000135db2c": "sinmathew@nearko.com", "59b651dfe3567a0001d9bea8": "jeremy.burton@rea-group.com", "59b654175a8b5b00013113de": "roman.buchert@googlemail.com", "59b651eae3567a0001d9beaa": "1977Avan@googlemail.com", "59b652cae3567a0001d9bee3": "m.carl0380@gmail.com", "59b6531bfaeeee0001d1e661": "morten.larsen@vestreviken.no", "5a0179b1f5947d0001163146": "cataria03@gmail.com", "59b653275a8b5b000131139e": "adhamenaya@gmail.com", "59b651390edf79000135da70": "andrea.muccin@gmail.com", "59b652210edf79000135daa5": "timlundse26@gmail.com", "59b65516faeeee0001d1e6ee": "vincenzo_intermite@libero.it", "59b652f05a8b5b000131138e": "jivan1103@gmail.com", "5a031e5ca107160001a5a26a": "schaefer@arsu.de", "59b6550be3567a0001d9bf81": "jboucher@sopfeu.qc.ca", "5a021d60f378320001a1fa72": "jalevi@yahoo.com", "5a1ed4bd04272c0001e8478e": "cameron.jac@gmail.com", "59b6526de3567a0001d9bec8": "hajazi@gmail.com", "59b6538e5a8b5b00013113bb": "wfth69@gmail.com", "59b654c9e3567a0001d9bf6d": "contact@ebii.fr", "59b6533dfaeeee0001d1e667": "paula.roiges90@gmail.com", "59b65129faeeee0001d1e5d6": "ralf.schwarz@me.com", "59b6511ee3567a0001d9be80": "guerreiro.nma@gmail.com", "59b655d55a8b5b0001311448": "jwgvanderlichte@gmail.com", "59d6234061be6d0001ece833": "hummerzer@t-onlie.de", "59b652ace3567a0001d9bedc": "c.meddah@digital-ink.it", "59b65416faeeee0001d1e6aa": "a.lurz@prospega.de", "59b653e40edf79000135db36": "eltowfiq@gmail.com", "59f539fb53204c0001f0ad8c": "Jeff_german26@hotmail.com", "59b6513bdac3350001574fa5": "alecmattu1234@gmail.com", "59dca08bb8125f000137677a": "steventaylor78@gmail.com", "59b652875a8b5b000131136e": "vfconseil@friconneau.fr", "59b651c2faeeee0001d1e5fc": "parham728@gmail.com", "59b6526ffaeeee0001d1e62e": "kaminski.szymon33@gmail.com", "59b6522ce3567a0001d9beb6": "alberto.riva.26@gmail.com", "59b6532be3567a0001d9befc": "walkingtohorizonvp@gmail.com", "59ea1aba1080ef0001a166a8": "gdheesmann@htp-tel.de", "59f73278b8125f0001376ac0": "andreysoloweb@gmail.com", "5a2d22d1bb780c00017b4f84": "ralf-66@gmx.de", "5a1b818ff0a16100010f6410": "clouddo8788@yahoo.com.tw", "59b653165a8b5b0001311399": "mb@bits.at", "59b6524de3567a0001d9bec2": "akiptoo@gmail.com", "5a16a8846c48210001771e83": "dvanbo14@student.aau.dk", "59b65124dac3350001574fa2": "f.mauthner@aee.at", "59b652495a8b5b000131135d": "l503376@mvrht.net", "59b6550ee782050001d67152": "louisa.sorrentino@veitchlister.com.au", "59b655cfe3567a0001d9bfa9": "gusela@alice.it", "59b6539b0edf79000135db1d": "donald.westacott@halliburton.com", "5a1eba3004272c0001e84782": "ggoudvis@hotmail.com", "59b6541fe3567a0001d9bf43": "qaziwaqaskhalid07@gmail.com", "59b6556ee782050001d67169": "felix.bordea@holovision.ro", "59b6510d5a8b5b0001311309": "b.taborowski@placematic.pl", "59d4637d66d3930001b1bd8c": "mail.openrouteservice@bbayer.net", "59b6535c5a8b5b00013113ac": "klaus.vorwalder@tuttlingen.de", "5a0452700145d600016ce75b": "mateusgfelini@gmail.com", "59b65529e3567a0001d9bf86": "christou.george@ucy.ac.cy", "5a032004a107160001a5a26b": "mdhofmann@gmx.net", "59fca09c7fee5d0001b5cbaf": "beconnect@madrassaboutique.com", "59b65541faeeee0001d1e6fb": "jbiagio@ci.porterville.ca.us", "59b65561e3567a0001d9bf93": "andrew.g.whyte@gmail.com", "59b6532d5a8b5b00013113a0": "andreas.weiden@arcor.de", "59b652380edf79000135daae": "roberto.delavy@gmail.com", "59b651b0e3567a0001d9be9c": "george.solymosi@gmail.com", "59fb5799144ad1000197c4d2": "hieuhuynh1407@gmail.com", "59b6551be3567a0001d9bf82": "chris.altmayer@sympatico.ca", "59b65350faeeee0001d1e66a": "fieldcj@gmail.com", "59b653fc0edf79000135db3d": "lcmwesterink@gmail.com", "59b653ba5a8b5b00013113c5": "andrew@hannell.com", "59b65193faeeee0001d1e5f5": "Justin.k.helms@gmail.com", "5a2e90782c8add00019eb055": "nils@trump.com", "59b6546d5a8b5b00013113fb": "labprogterritorio@uniroma1.it", "59b6513ffaeeee0001d1e5df": "acct1004@yahoo.com", "59b653135a8b5b0001311398": "rafael@l8.vc", "59b651b35a8b5b0001311331": "mj@jungnickel.tv", "5a15047673b158000141ba70": "kmc926@naver.com", "59b653a70edf79000135db22": "stefaan.hallet@gmail.com", "59b65200dac3350001574fcf": "kristijans531@gmail.com", "59b653d10edf79000135db2e": "annesophie.odorico@iprospect.com", "59b654a1faeeee0001d1e6d0": "rationtai@gmail.com", "59b655660edf79000135db90": "m.a.booden@gmail.com", "59cc3fa4adcedb00014a6d39": "hugo.garcia@live.com.pt", "59b65564faeeee0001d1e704": "rubenmg@usal.es", "59b652440edf79000135dab1": "jasper.michalke@jasmich.de", "59b651d6e3567a0001d9bea4": "christian.meyer@yahoo.de", "59d4f79c046934000198aad9": "alex.halevin@gmail.com", "59b65468e3567a0001d9bf56": "wiedzie@yahoo.com", "59b655a35a8b5b000131143e": "bonushenricus76@gmail.com", "59b6514cdac3350001574fa8": "sindile.bidla@geoilocate.co.za", "59b65398faeeee0001d1e67e": "juerg.lindauer@bluewin.ch", "59b6519a0edf79000135da8a": "saar@innovid.com", "59b653010edf79000135dae4": "titovvlad1997@yandex.ru", "59b651770edf79000135da80": "pratik@mail.harvard.edu", "59b65527faeeee0001d1e6f3": "franco.nicola@gmail.com", "59b65426e3567a0001d9bf45": "openrouteservice@anom.ru", "59b65377e3567a0001d9bf11": "cja97@email.arizona.edu", "59b654810edf79000135db66": "jo.ellis2801@yahoo.co.uk", "59b655195a8b5b0001311426": "ekangu@ekangu.eu", "59b650f75a8b5b0001311303": "apurvamaloo4@gmail.com", "59db67135f1f44000186227e": "nourredine.idir@aurca.org", "59b654955a8b5b0001311407": "svassen@gmail.com", "59f0da8db8125f0001376a3b": "daoane@gmail.com", "59b654eefaeeee0001d1e6e5": "rjustribo@muns.es", "59b651180edf79000135da68": "martin.noth@afsta.karlsruhe.de", "59b653255a8b5b000131139c": "taimurknaziri@gmail.com", "59b65183faeeee0001d1e5f0": "kenovaf@gmail.com", "59b65183faeeee0001d1e5f1": "endadabenda@yahoo.de", "5a1b73edf0a16100010f63ec": "qqa123456123@yahoo.com.tw", "59b65559e3567a0001d9bf90": "matthew.dowell@rmsurveys.com.au", "59ee6636b8125f00013769ef": "adrien.calvezpetit@gmail.com", "59b6545fe3567a0001d9bf54": "marvin.thoene@web.de", "59b65169dac3350001574faf": "ju.torin@gmail.com", "59b65115faeeee0001d1e5d0": "megateleporter777@gmail.com", "59b65211e3567a0001d9beb0": "markus.hessler@gmx.net", "59f3b3d2edee8500019df5f1": "urveekarve@gmail.com", "59b65422e3567a0001d9bf44": "Matvei.PR@gmail.com", "59b652c3faeeee0001d1e647": "ganeshyogesh05@gmail.com", "59b655ba5a8b5b0001311444": "nternent@rsk.co.uk", "59b654bb0edf79000135db73": "kozeban@mail.ru", "59b65560e782050001d67166": "katja.froehlingsdorf@rwth-aachen.de", "59b6514e5a8b5b0001311317": "dietrich.mtths@googlemail.com", "59b6543f0edf79000135db4f": "kasper@cfbo.dk", "59e796eecbddb50001d5e207": "marco.rios@eeh.hn", "59b651e8faeeee0001d1e606": "georgiyar@gmail.com", "59b65239faeeee0001d1e61a": "ucostantini72@hotmail.com", "59b653295a8b5b000131139f": "office@aim-media.at", "59b65340e3567a0001d9beff": "soukaroma@me.com", "59d7b55732c7160001b7eaf3": "markus@legner.ch", "59b65413faeeee0001d1e6a8": "jerzyryszardkapciak@gmail.com", "59b652605a8b5b0001311366": "fotios.xystrakis@gmail.com", "59b6529afaeeee0001d1e63b": "raquelsaraiva26@gmail.com", "5a13f9a3f8d24b0001f50fbd": "501276178@qq.com", "59b652d00edf79000135dad4": "f1k314li@gmail.com", "59d468883468de0001650ad2": "451759613@QQ.COM", "59b650f3dac3350001574f97": "peter@prajczer.eu", "59b65239faeeee0001d1e619": "pescale@gmail.com", "5a1b7213f0a16100010f63d9": "chen125705478@gmail.com", "59b650f9faeeee0001d1e5cb": "daninvo@gmail.com", "59eef0130a2a600001782cc3": "roland.raab@ppoe.at", "59b652be0edf79000135dacd": "kashirasingh7@gmail.com", "59b65523e782050001d67159": "ivan@ditat.net", "59b652affaeeee0001d1e640": "jorge.munoz@sag.gob.cl", "59b655a9e782050001d67174": "ivan.nasution@gmail.com", "59b6535afaeeee0001d1e66e": "trvmrz@gmail.com", "59b6549d0edf79000135db6c": "b.j.kobben@utwente.nl", "5a2ec96a11e8e60001eafe3b": "moraleskimbrian@yahoo.com", "59cf6ec8b8125f000137660a": "gerd@diro-online.com", "59b6517de3567a0001d9be91": "chuzzlewit69@gmail.com", "59b651055a8b5b0001311307": "4makseg@gmail.com", "59f6f662a2387d0001ef0a93": "elias.pajares@hotmail.de", "59b654750edf79000135db63": "pawel.bierkowski@gmail.com", "59b655b60edf79000135db9e": "lkm@geopartner.dk", "59b652d1faeeee0001d1e64a": "reece.pomeroy@gmail.com", "59b6547e0edf79000135db65": "roke@euskalnet.net", "59b653aafaeeee0001d1e684": "ernie60415@yahoo.com.tw", "59b653c2faeeee0001d1e68d": "ing.guidorossi@gmail.com", "59b652a05a8b5b0001311376": "xxxxxxx@xxxxxxxxxxx.x", "59b6514be3567a0001d9be88": "562679654@qq.com", "59b6533e5a8b5b00013113a5": "marco.brugna@gmail.com", "59b6529ae3567a0001d9bed6": "cvetlicni@gmail.com", "59b651b20edf79000135da90": "lvizatelle@gmail.com", "59b65150dac3350001574faa": "crrnqp@gmail.com", "59b650e30edf79000135da5e": "rajat.lutade@mediaagility.com", "59b6541de3567a0001d9bf42": "nrbrigmon@gmail.com", "59b6538d5a8b5b00013113ba": "enricorusso60@gmail.com", "59b652700edf79000135dab9": "daniel.gebauer22@gmail.com", "59b654f3e3567a0001d9bf78": "gbmn94@gmail.com", "59b6538afaeeee0001d1e678": "petter37@web.de", "59b6532f5a8b5b00013113a2": "son.k_a@tlen.pl", "5a09aea382ee7c00012d54cf": "event@fu-berlin.de", "59b6546cfaeeee0001d1e6bf": "testa@dreamwall.be", "59b65114e3567a0001d9be7c": "roman.kolenda@jet-bi.com", "59b653460edf79000135db00": "m.fuss@prospega.de", "59b654285a8b5b00013113e5": "info@isdebrugopen.nl", "5a10764b1b43920001dc787b": "zijmztql@eelmail.com", "59b6518d0edf79000135da87": "tillgottschalk1@web.de", "59b6513cfaeeee0001d1e5de": "mccomb@ltmgt.com", "59f844820ebff7000188cbd1": "mickael.mouton@gmail.com", "59f4f047b8125f0001376a93": "nicotenios@gmail.com", "59b651420edf79000135da72": "woodleejc@qq.com", "5a201506e150180001037550": "stefan.irmgard.koch@hotmail.de", "59b651ff0edf79000135daa1": "petrik13@gmail.com", "59b651c3e3567a0001d9bea0": "isa_fahrenholz@yahoo.de", "59b655aae782050001d67175": "gigigui@hotmail.com", "59b65188faeeee0001d1e5f2": "ross.cullen@talisconsultants.com.au", "59b6534b0edf79000135db03": "ivo.hauer@ils.brk.de", "59b6545ae3567a0001d9bf53": "t.eames@frlcraft.com", "59b6537ee3567a0001d9bf14": "lipandes@gmail.com", "59b653000edf79000135dae3": "yannis.pigorsch@gmx.de", "59c26a977e6168000145da2c": "bcohen@csc.csiu.org", "59b650f6dac3350001574f99": "ana.keylouli@gmail.com", "5a11c3652767a50001625a15": "vferrand@citadia.com", "59d39ccae8692a0001026670": "hartzfear+openrouteservice.org@gmail.com", "59b654420edf79000135db51": "elfekhar.inssaf@gmail.com", "59b65553faeeee0001d1e701": "ardil.gulez@citysurf.com.tr", "59b65496e3567a0001d9bf60": "kaiserin@diekaiserin.at", "59b65204e3567a0001d9beae": "paul.mmoja@yahoo.com", "59f08e0d105fb100010d5ee7": "hartwig@wanderfreude.de", "59fcb8030930580001f09420": "david.eberhardt@weinig.com", "59b65521faeeee0001d1e6f1": "criutcenco@gmx.de", "59b653cb5a8b5b00013113c8": "bbuhagiar@laingorourke.com.au", "59b650e85a8b5b0001311301": "j.heblinski@geosystems.de", "59b65491e3567a0001d9bf5f": "morten@styrke10.dk", "5a1590841252e50001546c73": "s113290@student.dtu.dk", "59b65502e3567a0001d9bf7b": "biomodel.vm.gri@gmail.com", "59b65502e3567a0001d9bf7c": "gordon.finn@csconsulting.ie", "59d86509a34f170001c6d4f6": "michael.schmidtke@unitybox.de", "59b6544e5a8b5b00013113ef": "marijo.maracic@gmail.com", "59b652980edf79000135dac3": "thoralf.stein@tu-berlin.de", "59b65222faeeee0001d1e615": "ralph.hughes@sustrans.org.uk", "59b653800edf79000135db16": "carlo.bertelli@gmail.com", "59b653e8e3567a0001d9bf33": "rotin21@naver.com", "59b652245a8b5b0001311352": "matthewaoss@gmail.com", "59b654805a8b5b0001311401": "seanlee61275@gmail.com", "59b654a70edf79000135db6e": "saii5auren@gmail.com", "59b653480edf79000135db01": "bard83@gmail.com", "59b654bee3567a0001d9bf6a": "n.kolev@vm5.eu", "59ccbc6d27e0f100018c4354": "r.tockner@live.at", "59b653230edf79000135daf0": "wendel@eifer.org", "59b65264e3567a0001d9bec6": "nfalconersa@gmail.com", "59b653d6faeeee0001d1e694": "mark@nothingmore.co", "59b651200edf79000135da6a": "hi@appbureau.co", "59b653850edf79000135db18": "joseph.mcmahon@digitalglobe.com", "59b653c00edf79000135db29": "giorgio-43@hotmail.it", "59ef1c5c0508520001a69c54": "philippbenz@gmx.de", "59b655800edf79000135db94": "urbanistalepe@gmail.com", "59b653030edf79000135dae5": "r@t.co.uk", "59b651815a8b5b0001311321": "klovelace@hotmail.com", "59d7c8961216c600017988d5": "kellygdell@gmail.com", "59b654d8faeeee0001d1e6e0": "m.bruckner@eyecoon.at", "59b6547bfaeeee0001d1e6c5": "meskovic@me.com", "59e5c51fee2ed60001583f9d": "alina-n-97@web.de", "59b6552b0edf79000135db83": "talesbeltrao@gmail.com", "59b65527e3567a0001d9bf85": "cf@eshamburg.de", "59e8a54e6499ef000175be35": "eleanordharris@hotmail.com", "59b65450faeeee0001d1e6b7": "xtotut@gmail.com", "59b653dce3567a0001d9bf2f": "office@gorge.co.nz", "59b653a55a8b5b00013113bf": "fritz4@gmail.com", "59b653ab5a8b5b00013113c1": "derzhi@hotmail.co.uk", "59b652180edf79000135daa4": "jessie_yuan@yeah.net", "59b6543f0edf79000135db50": "vignesanselvam@gmail.com", "59b655b30edf79000135db9d": "contato@confirm8.com", "59b651595a8b5b000131131a": "jahangard.sirvan@gmail.com", "59b655a75a8b5b0001311441": "ckoettl@gmail.com", "59b651595a8b5b000131131b": "matthieu.carlini@haute-vienne.chambagri.fr", "59b6536de3567a0001d9bf0e": "wilsoncardosomail@gmail.com", "59b654465a8b5b00013113ed": "dschlamp@argusproperties.ca", "59b6555d5a8b5b0001311432": "simonp.warren@gmail.com", "59b654245a8b5b00013113e4": "vitor.quintanilhabarbosa@barcelonagse.eu", "59b651b8e3567a0001d9be9e": "vpbonenfant@voyagezfute.ca", "59b652805a8b5b000131136c": "shane.french@dbca.wa.gov.au", "59b653370edf79000135daf8": "gianluca.faletti@top-ix.org", "59b6558b5a8b5b0001311436": "urpolski@gmail.com", "59b65549e782050001d67161": "ty33d0g@gmail.com", "59b651dcfaeeee0001d1e604": "juan.jaraices@beeva.com", "59b651300edf79000135da6d": "felicity.j.walker@gmail.com", "59b651005a8b5b0001311306": "ariefhidayatuin@gmail.com", "59b6546c0edf79000135db60": "mysterymann78.am@gmail.com", "59b65269e3567a0001d9bec7": "roman.angelov@gmail.com", "59b653c40edf79000135db2b": "Ute.Biegelmann@marktundstandort.de", "5a010f18b2a6e000016cd902": "rekoner57@gmail.com", "59b650715a8b5b00013112f7": "nwilkens@uni-bremen.de", "59b652b8faeeee0001d1e643": "amaury.boulin@rentokil-initial.com", "59b65411e3567a0001d9bf3f": "ramon.noguer@gmail.com", "59b653540edf79000135db08": "andreas.kuebart@gmail.com", "59b655780edf79000135db93": "polsti@googlemail.com", "59b65538e782050001d6715e": "gdecil@gmail.com", "59b652235a8b5b0001311351": "ndurou@ollwin.com", "59b652740edf79000135dabb": "karl.6180@gmail.com", "5a1d245ac05dd4000136a811": "christiane.becker@kompassnachhaltigkeit.de", "59b654930edf79000135db6b": "thomas@souvignet.net", "59b65381faeeee0001d1e675": "fanette.1@youplaboum.fr", "59b655a6e3567a0001d9bf9e": "gelagalle+ors@gmail.com", "59b653c7faeeee0001d1e691": "lisa.jarzembowski@outlook.de", "59b651550edf79000135da78": "Koerbelchristof@web.de", "59b654f95a8b5b000131141e": "luc.gabriel@live.com", "59f5c83ca2306d00017301db": "fabiene@dold.ws", "59b653ae5a8b5b00013113c2": "info@shareyourmountain.com", "59b65310faeeee0001d1e65c": "r.kitzing@ptsgroup.de", "59b653e9e3567a0001d9bf34": "verschueren.paul@telenet.be", "59b654fd0edf79000135db7c": "wolf.pulheim@freenet.de", "59b655cee3567a0001d9bfa8": "george.dickinson@gmail.com", "59b65372e3567a0001d9bf0f": "a.perugini@easycloudcompany.it", "59b65259e3567a0001d9bec3": "Joachim.Langshausen@t-online.de", "59b652730edf79000135daba": "nbyrne16@gmail.com", "59b6525fe3567a0001d9bec4": "brtsz.kolasinski@gmail.com", "59b650f8dac3350001574f9a": "schuettler.dietmar@gmail.com", "59b65246e3567a0001d9bec0": "bmnewman@umd.edu", "59b650f40edf79000135da61": "wmccutcheon@mrleng.com", "59b65397e3567a0001d9bf1a": "marcello.campagna@aduno-gruppe.ch", "5a04772c4fea610001339dc8": "pierreptraba@gmail.com", "59b6548bfaeeee0001d1e6cb": "mark@healthsites.io", "5a0eab02f713d90001a8dedf": "nnicolasmoguen@hotmail.com", "59b6533b0edf79000135dafb": "openrouteservice.20.loled@xoxy.net", "59b65146dac3350001574fa6": "isaacchikutukutu@gmail.com", "59b650665a8b5b00013112f5": "maurice.glandrup@nexusz.com", "59b651355a8b5b0001311311": "thomas.lehrack@webxells.com", "59b65219faeeee0001d1e611": "mleduc@lestoux-associes.com", "5a245e79c158e300013edbe7": "alhabbalnour@gmail.com", "59b651e00edf79000135da9b": "jose@yopmail.com", "59b651b6e3567a0001d9be9d": "a.m.fulterer@aee.at", "59b6539ce3567a0001d9bf1c": "Map@ramboll.dk", "59b6528afaeeee0001d1e638": "andrew.smith@emp.shentel.com", "59b6540cfaeeee0001d1e6a6": "robr@trondheim.kommune.no", "59b65273faeeee0001d1e631": "lmedina@wesleyan.edu", "5a13fe0eafc98c0001d57405": "buschi_auf_reisen@web.de", "5a2f3f07e3fbf30001f46160": "d.a.webb.sunbury@gmail.com", "59b6515efaeeee0001d1e5e5": "jmm@catl.be", "59b651360edf79000135da6f": "yiyanggis@gmail.com", "59b65599e782050001d67171": "claire.lallier92@gmail.com", "59b654ffe782050001d67150": "igor@cmssolutions.rs", "59b655930edf79000135db97": "michel.neuhengen@gmail.com", "59c3dc665442880001833ec0": "acws@gmx.net", "5a28e64d854a320001de960b": "iad93072@xoixa.com", "59b65272faeeee0001d1e630": "avidalgomez@gmail.com", "5a1b73967cd6870001d39b34": "zexal125705478@gmail.com", "59b653665a8b5b00013113af": "suwear@getnada.com", "59b654c25a8b5b0001311416": "Czubek@abm-service.de", "59b6514f0edf79000135da77": "markus.kortuem@remondis.de", "59b6536f5a8b5b00013113b4": "eng.tiagos@gmail.com", "59b654a0e782050001d67137": "colin.dalton@eir.ie", "59b65422faeeee0001d1e6ae": "bokotey.s@gmail.com", "5a0183b6bc991600013baca1": "sfilter@interia.pl", "59b654da5a8b5b0001311419": "l.mauchain@gp3a.bzh", "59d63c9a61be6d0001ece835": "it@barbara-reisen.de", "59b655d3e3567a0001d9bfaa": "addi.spam@yahoo.de", "59b6528d0edf79000135dac2": "xcode_user@yahoo.com", "59b651d4faeeee0001d1e601": "jcarpenter@providencegroup.com", "59b651e0e3567a0001d9bea9": "yustanujulmakap@gmail.com", "59b65521e3567a0001d9bf83": "martin@kucharzewski.de", "59b653300edf79000135daf4": "thomas.ryan@outlook.com", "59b652975a8b5b0001311373": "mail@juliuste.de", "59b655525a8b5b000131142f": "saliola.francesco@gmail.com", "59b65517faeeee0001d1e6ef": "stefan.falke@gmail.com", "59b651dde3567a0001d9bea6": "juergenpott@googlemail.com", "59b653420edf79000135dafe": "gerwinbosch@chello.nl", "59b654e5faeeee0001d1e6e3": "bichobicharejo@gmail.com", "59b6516ddac3350001574fb0": "leo.fhumar@gmail.com", "59b6541ae3567a0001d9bf41": "lwidder13@gmail.com", "59b714a7fb04870001b45e07": "piotrlukowski3@gmail.com", "59b65537faeeee0001d1e6f8": "dinis.joel@gmail.com", "59f84efe144ad1000197c482": "kanoti2002@yahoo.com", "59b654775a8b5b00013113ff": "florent.cholat@gmail.com", "59b6543de3567a0001d9bf4c": "jamesb@aspinallverdi.co.uk", "59b6510bfaeeee0001d1e5ce": "shobmaz@gmail.com", "59b6553a0edf79000135db88": "r.triebel@pv-muenchen.de", "59b65161e3567a0001d9be8c": "guido@schratzer.at", "59b65482faeeee0001d1e6c6": "woschof@gmx.de", "59b6542ee3567a0001d9bf48": "umutkarakulak@hotmail.com", "59b65504e3567a0001d9bf7d": "mail.emaproject@gmail.com", "59b654ede782050001d6714a": "dominik.abend@gmx.de", "59b65427e3567a0001d9bf46": "Abdullah_33@hotmail.de", "59b651d75a8b5b0001311339": "louise.drocourt@gmail.com", "5a1dabc4e243250001637f0f": "ti@forter.com.ua", "59b6551ee782050001d67157": "ateixido@yahoo.com", "59b651a05a8b5b000131132b": "augustin-chardon@orange.fr", "59b654f55a8b5b000131141d": "Moritz.Lipfert@gmx.de", "59b653f6faeeee0001d1e6a1": "4brianadi@gmail.com", "59b653bfe3567a0001d9bf26": "petermoavero@hotmail.it", "59b6506e5a8b5b00013112f6": "harmenstremler@outlook.com", "59b6558ce3567a0001d9bf99": "m.el-haddad@tup.com", "5a2011fe7b6fad00015577cf": "sascha.wittich@altensteig.de", "59b650fb0edf79000135da63": "romain.seigne@live.fr", "59f97a8bdb54870001a2a969": "mail@gerlinde-schiffer.de", "5a01b5530542e60001d7ffb3": "lucasstosbezerra@gmail.com", "5a2d7d29b2a38d00016d5988": "helmut.schelling@vector.com", "59b654bbe782050001d6713a": "lucas_andres_92@hotmail.com", "59b6542ffaeeee0001d1e6b2": "nordine@valog.fr", "59b6544afaeeee0001d1e6b5": "edvardas.minkevicius@arsa.lt", "59b65132e3567a0001d9be83": "ades_six@orange.fr", "59b6511ddac3350001574fa1": "Info@growfactor.ru", "59b654e2e782050001d67147": "grauefeder@gmx.de", "59b6527ae3567a0001d9becb": "steve@ridgelineintl.com", "59b65403faeeee0001d1e6a3": "fhdalyhya@gmail.com", "59b65591e782050001d6716f": "ktakase@tcg.co.jp", "59c92e0197dcca0001ff9d6e": "peut.w@t-online.de", "59b6513a5a8b5b0001311312": "enricofer@live.com", "59b653bcfaeeee0001d1e68c": "thomas.drewes@erzbistum-paderborn.de", "59b6543c0edf79000135db4e": "e.poeze@viriciti.com", "5a240292f2e0590001cdc7a0": "orlando_andrade@live.com.mx", "5a1669ca62f11f000146e718": "tx8n-ysg@asahi-net.or.jp", "59b65242faeeee0001d1e61d": "tyler.holmes@shell.com", "59b65568e782050001d67167": "eichler@adva.de", "59b65189dac3350001574fb6": "nicolas.boonaert@gmail.com", "59b65189dac3350001574fb5": "jwgarcia003@gmail.com", "5a144b9df62eec0001f0af7d": "toto@free.fr", "59b652bce3567a0001d9bee1": "jeff.daraujo@gmail.com", "59b653dfe3567a0001d9bf30": "winfried@strittmatter.info", "59b654d50edf79000135db76": "joseph_pawelski@avalonbay.com", "59b654a4faeeee0001d1e6d1": "adro.andre@gmail.com", "59b653435a8b5b00013113a6": "steven.de.lausnay@indeff.com", "59b653495a8b5b00013113a7": "st_kiefer@web.de", "59b651eefaeeee0001d1e607": "freestone.panoramio@gmail.com", "59b652c20edf79000135dacf": "cocoyote@gmail.com", "59d9021851f60100011f1fde": "baerbel.koch@hotmail.com", "59b65383faeeee0001d1e676": "shineon82@gmail.com", "5a1b9e3cf56b9200019201d2": "asmithresho0@gmail.com", "59b653660edf79000135db0e": "peter@drhzbg.de", "59b652dafaeeee0001d1e64d": "bh001@yandex.ru", "59b654e90edf79000135db79": "atte.lof@gmail.com", "59b655c4e782050001d6717b": "bjornarremm@gmail.com", "59b651c5e3567a0001d9bea1": "nick61@gmail.com", "5a253408abae7400011c3325": "nuri.oernek@gmx.de", "59b6534a0edf79000135db02": "pigrecoinfinito@gmail.com", "59b652d90edf79000135dad7": "mapa_olt@hotmail.com", "59b651fddac3350001574fce": "Paul.Archambault@pb.com", "59b6522a5a8b5b0001311354": "Kerrajgis@gmail.com", "5a02bff6e426ed0001e77f40": "sd171017@g.hit-u.ac.jp", "59b655d4e782050001d6717f": "notmva@gmail.com", "59b6556ce782050001d67168": "daniel.hoelzlhammer@sfs-w.bayern.de", "59b65570e3567a0001d9bf97": "travis4fun@sbcglobal.net", "59b651690edf79000135da7c": "bureauduplan@wanadoo.fr", "59b654a30edf79000135db6d": "mail@urbanfix.eu", "59b6505ddac3350001574f8a": "gilbert@gk2.d", "59b653065a8b5b0001311394": "gabriel.bengtsson@lm.se", "59f1d83673429900015a604c": "raymondw@web.de", "59b654005a8b5b00013113d4": "tiagochi@gmail.com", "59b651565a8b5b0001311319": "fedelang@gmail.com", "59b6544cfaeeee0001d1e6b6": "julienlesbegueries@gmail.com", "59b652c1faeeee0001d1e646": "clementhamon@gmail.com", "59b652fafaeeee0001d1e657": "jsantos@newarkcedc.org", "59b65208dac3350001574fd2": "karen.schulz@herne.de", "59b650fe5a8b5b0001311305": "wang@longqi.cf", "5a11ae494207f2000112eefc": "jonas.irmler@hof-university.de", "59b65248faeeee0001d1e61f": "jan.franta@tdg.co.nz", "59f33cd6b8125f0001376a7b": "michel.jeannenot@mobhilis.fr", "59b65474e3567a0001d9bf57": "qwqw@posteo.de", "59b652290edf79000135daa9": "wenyu93@gmail.com", "59b65359e3567a0001d9bf05": "pyarchinit@gmail.com", "59b654f6e3567a0001d9bf79": "georg.hage-huelsmann@outlook.com", "59b652405a8b5b000131135b": "moritz.rengert@gmail.com", "59b655555a8b5b0001311430": "andrem@mit.edu", "59b65465e3567a0001d9bf55": "herrmann.andre@bluewin.ch", "59b6541a0edf79000135db42": "carlocimenezes@gmail.com", "59bbb2e9424d7c0001c66e68": "kbro@muenster.de", "59d9048d51f60100011f1fdf": "snobzee84@gmail.com", "59b6558f0edf79000135db96": "buhrots@gmail.com", "59f96570db54870001a2a968": "shashi.upes@gmail.com", "59b65106e3567a0001d9be77": "support@dmmhehe.com", "59ef6a88b8125f0001376a03": "fre.hub@gmail.com", "59b65498faeeee0001d1e6ce": "christopher.moulton.knight@gmail.com", "59b650e6dac3350001574f95": "oscar.schindler@gmail.com", "59b654595a8b5b00013113f5": "dennis.becker@dean.com", "5a1bc7e619e2c40001b9fe64": "rosse@isw-gmbh.de", "59b6512bfaeeee0001d1e5d7": "algee615@gmail.com", "59b650d4e3567a0001d9be6e": "mauriceallen67@gmail.com", "59b651105a8b5b000131130a": "daf08@hotmail.com", "59b654335a8b5b00013113e7": "xpirixii@gmail.com", "59b654d3e3567a0001d9bf6f": "can@iyiofis.com", "59b65399faeeee0001d1e67f": "mauro_benza@yahoo.it", "5a09eac76126ba00015d0e82": "hkeukenmee@cs.com", "59b654eb5a8b5b000131141c": "lefebvre.step@gmail.com", "59f8f2c3d4c77900015fb01a": "sbitiali@gmail.com", "5a0c27c100188f0001e81395": "c.paolillo@u-s.it", "59b653cc0edf79000135db2d": "bakker.vita@gmail.com", "59b653c5faeeee0001d1e68f": "it@transdata.sk", "59bc3a656070ca0001f62949": "tsantsan@gmail.com", "59b650d00edf79000135da5c": "bisiteandroid@gmail.com", "59b6513ae3567a0001d9be85": "cornel.marcu@ecocomputer.com", "59b651a9faeeee0001d1e5f8": "milancaspers@gmail.com", "59b65450e3567a0001d9bf51": "antonio.tovar.chavez@gmail.com", "59e1e9490d3f800001d0890f": "bischof.stutensee@gmail.com", "59b652e25a8b5b0001311389": "matten.lindemann@gmx.de", "59b651340edf79000135da6e": "kim.ledinh@navocap.com", "59b65234e3567a0001d9beb9": "fichrist@gmail.com", "59b6537c0edf79000135db15": "aksum23@gmail.com", "5a0445e62277930001e32ef9": "i.dimarcello@libero.it", "59b65138faeeee0001d1e5dd": "ade@agora-urba.be", "59b6552cfaeeee0001d1e6f6": "Hubert.verreault@polymtl.ca", "59b6545e0edf79000135db5c": "serge.herviou@aurca.org", "59b650f2e3567a0001d9be72": "tpodgorskirr@gmail.com", "59b653ddfaeeee0001d1e696": "c.hettenbach@iib-institut.de", "59b65530faeeee0001d1e6f7": "dinesh.c@redbus.com", "59b65166dac3350001574fae": "Kristinas@mjaconsulting.co.uk", "59b655390edf79000135db87": "sarbiewski@t-online.de", "59b6510ee3567a0001d9be7a": "marco.schmidt@jkarat.de", "59b655cce782050001d6717c": "albert.keba@gmail.com", "59b654ddfaeeee0001d1e6e2": "pelle@andreapellegrini.net", "59b654e8faeeee0001d1e6e4": "mbrunsdon@healthpi.com.au", "59b6517bdac3350001574fb3": "neil.carr@callcreditgroup.com", "59b651450edf79000135da74": "willy.meesters@home.nl", "59b65550e782050001d67162": "tommigro@gmail.com", "59b655ae0edf79000135db9b": "anne-sophie.onody@agrocampus-ouest.fr", "59e9c8466491e40001bcc534": "sam.brown@rodgersleask.co.uk", "59b65493faeeee0001d1e6cc": "vilmajochim@web.de", "59b65554e782050001d67163": "dhar@camelot-mc.com", "59b653b4e3567a0001d9bf24": "montrudiz@yahoo.es", "59b65345e3567a0001d9bf02": "evabauer_@gmx.at", "59b652a50edf79000135dac7": "wib@gmx.at", "5a1bc43a19e2c40001b9fe63": "hamad29911992@gmail.com", "59b655d0e782050001d6717d": "jagutier20@gmail.com", "59f196f4dc902b0001753609": "pathmapper@posteo.de", "59b652bffaeeee0001d1e645": "tschroee@smail.uni-koeln.de", "59b652bffaeeee0001d1e644": "stefanovidiustoian@gmail.com", "59b6519b5a8b5b000131132a": "martin.wieser@geo.tuwien.ac.at", "59b653c8e3567a0001d9bf28": "mlui@naver.com", "59b65476e3567a0001d9bf58": "tjk1@clevelandmetroparks.com", "59b654d1e782050001d67141": "matias.andersson@bisnode.com", "59b6558ee3567a0001d9bf9a": "mchlebcova@csob.sk", "59b65277e3567a0001d9bec9": "m.biskupska@imm.org.pl", "59b6521cfaeeee0001d1e613": "denis@dwpayne.net", "59b65542e3567a0001d9bf8d": "khojasahil@gmail.com", "59b6536ce3567a0001d9bf0d": "sphanto@gmail.com", "59b65152faeeee0001d1e5e3": "chansen@atni.com", "59b65104e3567a0001d9be76": "plessl@pilger.de", "59b6522e5a8b5b0001311356": "jonathan.nicholson@cdcbus.com.au", "59b6523efaeeee0001d1e61c": "doug.lists@gmail.com", "5a180c4f1a36fe000184943f": "kucekovic.zoran@gmail.com", "59b6540d5a8b5b00013113da": "salomoni.anp@gmail.com", "59b6553e0edf79000135db89": "kupie.inwestycyjne@gmail.com", "59b65230faeeee0001d1e617": "abdallah.moussaoui@lecese.fr", "59b654125a8b5b00013113dc": "james.burn@gmblueplan.ca", "59b6546b5a8b5b00013113fa": "michael.saunders101@gmail.com", "59b655625a8b5b0001311433": "blpad@yopmail.com", "59b652275a8b5b0001311353": "miracomoloago@yahoo.com", "59b654dbfaeeee0001d1e6e1": "lukasjakrtek@gmail.com", "59b653c75a8b5b00013113c7": "galfau@gmail.com", "59b651eddac3350001574fc9": "max.bergmann@heidelberg-mobil.com", "59b654025a8b5b00013113d6": "kieran@paulcowieandassociates.com", "59b651a3e3567a0001d9be99": "nenad@id.com.au", "59b652090edf79000135daa2": "jan@pabyska.cz", "59b6551b5a8b5b0001311427": "xavier.paradell@xpfconsulting.com", "59b650c35a8b5b00013112fe": "erwan.carree@bnpparibas.com", "59fcd8eb144ad1000197c503": "H.Kipke@gmx.de", "59e6d2d1b8125f00013768e1": "Nasi.Racaca@rockingham.wa.gov.au", "59b6549c5a8b5b0001311409": "geert.smet@gmail.com", "59b65137faeeee0001d1e5dc": "dexter.stpierre@gmail.com", "59b652d80edf79000135dad6": "donavan.martin@usherbrooke.ca", "59b654215a8b5b00013113e2": "staehelid@hotmail.com", "5a30c699fff95000012db8eb": "harald.schoetterl@bruchsal.de", "5989c2c29547c1000111d577": "adam.rousell@uni-heidelberg.de", "59b6529fe3567a0001d9bed8": "rainer_schuetz1985@web.de", "59d64883b8125f00013766d0": "dtruscoe@gmail.com", "59b651915a8b5b0001311326": "sabrina.giegerich@googlemail.com", "59b65262faeeee0001d1e628": "br@ntmail.com", "59b65179e3567a0001d9be8f": "martin@merchandiser.ch", "59b65335faeeee0001d1e666": "guzik.damian.nt@gmail.com", "59b65335faeeee0001d1e665": "dofreda@gmail.com", "59e46676b8125f000137688b": "g.vincent.guillaume@gmail.com", "59b653390edf79000135daf9": "zammaissam@yahoo.fr", "59b6548be3567a0001d9bf5d": "pkardas@gmail.com", "59b65497e3567a0001d9bf61": "danielmatec@gmail.com", "5a02633a18288a00013477c7": "gsomogyi5@gmail.com", "59b651aae3567a0001d9be9a": "ozguryild@yahoo.com", "59b653bd5a8b5b00013113c6": "s.errazki@objectif-ville.com", "59b654ea5a8b5b000131141b": "fabian.staudinger@pixida.de", "59b651da0edf79000135da9a": "valerio.cuneo@hotmail.it", "59b65414faeeee0001d1e6a9": "txq1986@gmail.com", "59b6549c5a8b5b000131140a": "mountp@caerphilly.gov.uk", "59b65505faeeee0001d1e6e9": "lassegs@gmail.com", "59b651110edf79000135da67": "zlatko.horvat@live.unigis.net", "59b653705a8b5b00013113b5": "haeyun@gmail.com", "59b65083e3567a0001d9be6d": "Nico.Braun1@gmx.de", "59b65406faeeee0001d1e6a4": "denk.florian@googlemail.com", "59b65126e3567a0001d9be82": "boris@docupet.com", "59b65187e3567a0001d9be92": "aneculaiesei_silviu@yahoo.com", "59b6528f5a8b5b0001311370": "guidovos@gmail.com", "59ef27af1581c40001dcf48a": "w3lifer@gmail.com", "59b652a75a8b5b000131137a": "alain.dubois@agriculture.gouv.fr", "59b65436e3567a0001d9bf4a": "jungmin449@3waysoft.com", "59c31c326070ca0001f629f8": "alex.rangel@ameritek.com.ve", "59b6510fe3567a0001d9be7b": "owen@owell.cc", "59b65478e3567a0001d9bf59": "sportyspice@bluewin.ch", "59b6556de3567a0001d9bf96": "kasparas.lendraitis@gmail.com", "5a30cb833e118f0001a05385": "tino.lorenz@me.com", "59b650935a8b5b00013112fa": "route@mm13.at", "59b6517fdac3350001574fb4": "jjoy.work@gmail.com", "59b6554ffaeeee0001d1e6ff": "panbinbin11@gmail.com", "5a0a5e3afeec120001f97f99": "kiibiimorales@gmail.com", "59b651c3faeeee0001d1e5fd": "zemax@web.de", "59b652835a8b5b000131136d": "taff.franck@gmail.com", "5a1ec28f9af17900011dcab4": "antonio.cengija@centrallogistik.de", "59b655b4faeeee0001d1e713": "nuraxis@tiscali.it", "59b655bce3567a0001d9bfa2": "thomas@kadjy.dk", "59b651730edf79000135da7f": "philipp.heimeier@gmail.com", "59b65485faeeee0001d1e6c8": "yngve@gomobile.no", "59b654355a8b5b00013113e8": "hennessyab@gmail.com", "59b65133e3567a0001d9be84": "louish19alter@gmail.com", "5a0c29f5a9727b0001abd8d5": "antunez@puertomalaga.com", "59b651865a8b5b0001311323": "kevin@eii.fr", "59b651c15a8b5b0001311334": "naciocal@gmail.com", "59b6540afaeeee0001d1e6a5": "89ousmanetoure@gmail.com", "5a117b010cc2400001afb665": "amar@iith.ac.in", "59b6544f0edf79000135db56": "gemma@elrisell.cat", "59b655940edf79000135db98": "frederic.chapalain@gmail.com", "59b653a4e3567a0001d9bf1f": "katharina.mueller@mobilitaetsloesung.de", "59b65396e3567a0001d9bf19": "LUCY.WILSON@HACKNEY.GOV.UK", "59b654e0e3567a0001d9bf72": "hans-juergen.gau@lgln.niedersachsen.de", "59b6538bfaeeee0001d1e679": "qdb0201895321n@gmail.com", "59b65567e3567a0001d9bf95": "phillip.holroyd@live.de", "59b654520edf79000135db57": "agostino.trevaini@snamretegas.it", "59b6527dfaeeee0001d1e633": "vsokolova94@mail.ru", "59b651905a8b5b0001311325": "gungomanj@yandex.com", "59b652e85a8b5b000131138c": "carsten.hogertz@gmail.com", "59b65515faeeee0001d1e6ed": "jacco.verduijn@capgemini.com", "59d3aaf1df56c30001bd4190": "manuelfgnunes@gmail.com", "59b6534f5a8b5b00013113a9": "andre.storck@web.de", "59cddd5d11aa650001019cc5": "friedericir@e.mail.de", "59b65479faeeee0001d1e6c3": "J.jr.sampaney@live.de", "59f85dfd2364bc00013455c7": "csdybl@gmail.com", "59b65520e782050001d67158": "mathias.weber@med.uni-muenchen.de", "59b6531a0edf79000135daec": "geodarcy@gmail.com", "59b653b9faeeee0001d1e68b": "sven.huettermann@hcu-hamburg.de", "59b655a0e782050001d67173": "whitedave144@gmail.com", "59b6516f0edf79000135da7e": "guillermo.debernardo@udc.es", "59ce62d6d94b6400018c5451": "kommander-rosa@gmx.de", "59b6527c0edf79000135dabd": "querende@tcd.ie", "59b6553de3567a0001d9bf8b": "vtsyshnatiy@gmail.com", "59b6532e0edf79000135daf3": "david.muntal@yahoo.com", "59b655bffaeeee0001d1e718": "jacobaamark@gmail.com", "59b6515ffaeeee0001d1e5e6": "s3130103354@gmail.com", "59fcc0e9144ad1000197c4f9": "jaapdemotormuis@gmail.com", "59b6525d5a8b5b0001311364": "jacques.a.fournier@indicia.ca", "59b65597e3567a0001d9bf9b": "raquel.saraiva@youmanmod.com", "5a2ed34511e8e60001eafe3c": "al3xwolf2@gmail.com", "5a0376d424f3c900014ccc6a": "joshua.margul@burohappold.com", "59b6523dfaeeee0001d1e61b": "rh@keesmaat.nl", "59b651f8dac3350001574fcb": "philipknight@gmail.com", "59b6555ffaeeee0001d1e703": "atlasante@ars.sante.fr", "59b654890edf79000135db68": "smars27@gmail.com", "59b653f0faeeee0001d1e69e": "theyearis1999@gmail.com", "59b6515bfaeeee0001d1e5e4": "yura.smolyakov@gmail.com", "59b651f6e3567a0001d9beac": "clement.soenen@yahoo.fr", "59b651f75a8b5b0001311342": "sid.feygin@berkeley.edu", "59b653eafaeeee0001d1e69b": "chj@et.aau.dk", "59b65286faeeee0001d1e636": "gaec53270@orange.fr", "59e1dd84b8125f0001376842": "bischof.stutensee@t-online.de", "59b652a10edf79000135dac6": "armando_nrk@hotmail.com", "59b8b6246070ca0001f6288f": "alphafrauh@alphafrau.de", "59b6543b0edf79000135db4d": "jorishin@gmail.com", "59b6534d5a8b5b00013113a8": "sarah.hoessler@bntnz.co.nz", "5a07ce6e2a3c8b000114ffe3": "deathfire2345@gmail.com", "59f76abddd1b530001264926": "joriiis_@hotmail.fr", "59b6547fe3567a0001d9bf5b": "johannes.raps@tu-dortmund.de", "59b6543e5a8b5b00013113eb": "s.pichon@cabinet-ectare.fr", "59b654d9e3567a0001d9bf70": "otovhodued@gmail.com", "59b6536e5a8b5b00013113b3": "chuck.freeman@state.mn.us", "59b654c7e782050001d6713d": "ashalaby.uofm@gmail.com", "59b654290edf79000135db45": "caporin@infinito.it", "5a275afd93f7af0001e7a99d": "info4ele@yahoo.com", "59b652e60edf79000135dada": "Yaakov.FELDMAN@nao.gsi.gov.uk", "59b652e60edf79000135dadb": "josh@papertelevision.com", "59b651ebdac3350001574fc8": "makss@list.ru", "59b655b00edf79000135db9c": "maxim@friend.pl", "59b6558dfaeeee0001d1e70a": "alessandro.gigliarano76@gmail.com", "59b655a75a8b5b0001311440": "jonamgv@gmail.com", "59b65171dac3350001574fb2": "geberyt@gmail.com", "59b651bb0edf79000135da93": "spetrovic@rak.ba", "59b653fd5a8b5b00013113d3": "jackdocters@aol.nl", "59b6526afaeeee0001d1e62c": "savov@gis-bg.com", "59f061b8b8125f0001376a29": "sebastian.jeworutzki@ruhr-uni-bochum.de", "59b652d75a8b5b0001311388": "bruno.canessa@i-em.eu", "59bf32636070ca0001f62968": "wcui@coupang.com", "59f0b0c48df8de0001030c4a": "tjaart@dotxmltech.com", "59e32eedad098e000106d463": "t.balder@xs4all.nl", "59b65282faeeee0001d1e635": "petr.hajduk.aalto@gmail.com", "59e82705e9aa14000174c74a": "ho@correlate.at", "59b6520edac3350001574fd4": "simon@arnu.de", "59b652ec0edf79000135dadc": "jordi@amtu.cat", "59b65261faeeee0001d1e627": "lpl@midttrafik.dk", "59b653220edf79000135daef": "daurims@yahoo.com", "59b65499e782050001d67136": "arango@imn.ac.cr", "59b652cb5a8b5b0001311383": "risekote@hotmail.com", "59b655320edf79000135db86": "dummbatz.dummbert@gmail.com", "59f8246f144ad1000197c476": "skielboe@gmail.com", "59b652330edf79000135daac": "abdi.geovani@gmail.com", "59b65086dac3350001574f8d": "davidlamb@mail.usf.edu", "5a042f8ffd761100012ab584": "marc.schreiner@dwd.de", "59f453234aa39700017c35eb": "amandhol_4@hotmail.com", "59b651bf0edf79000135da95": "jamesbrett@georgefwhite.co.uk", "5a2ac3fa4817c40001ddc6ac": "niko.bobbenkamp@web.de", "59b65279e3567a0001d9beca": "kai.plambec@heilbronn.ihk.de", "59b6516edac3350001574fb1": "mafarough@gmail.com", "59b984d96070ca0001f628b0": "kbohn@die-bohns.de", "59b6508b0edf79000135da57": "Nadin.reissnegger@web.de", "59b6518ee3567a0001d9be93": "martinmicka@email.cz", "59b654585a8b5b00013113f4": "stefannrutten@gmail.com", "59b652dbfaeeee0001d1e64e": "iolit_m@mail.ru", "59b653f30edf79000135db3b": "ovskywalker@gmail.com", "59b654d7faeeee0001d1e6df": "rohan.weston@pandl.co.nz", "59b6547c5a8b5b0001311400": "rfilipov@gmail.com", "59b65113dac3350001574f9e": "james.blake@schroders.com", "59b653d70edf79000135db31": "yannik.lockner@googlemail.com", "59b654eee782050001d6714b": "sistemas@etsol.com.ar", "59b651bae3567a0001d9be9f": "sayzawn@gmail.com", "59b655cce3567a0001d9bfa7": "t.e.barnes17@gmail.com", "59b653b7faeeee0001d1e68a": "navidtaheri@gmail.com", "59b65296e3567a0001d9bed5": "andb@balk.dk", "59b6559ae3567a0001d9bf9c": "brett.meier@ngennetworks.com", "59b65463faeeee0001d1e6ba": "pier-luc@boudreault.ca", "59b6552ee3567a0001d9bf88": "p2w2@outlook.de", "59de2f50b8125f00013767d5": "levke-witthinrich@otmail.de", "59b65522e3567a0001d9bf84": "Claudia.Pinna@cumbria.gov.uk", "59b6530a0edf79000135dae7": "stevenkeersmaekers@agp-it.eu", "5a265c106c0d540001c1fb3b": "marijkemolema@live.nl", "59b650a55a8b5b00013112fc": "a.p.vazifehdoust@gmail.com", "59b651e3dac3350001574fc5": "helenavgh@hotmail.com", "59b652adfaeeee0001d1e63f": "mrjobosco@gmail.com", "59b65230e3567a0001d9beb7": "thomas.benelli@provinz.bz.it", "5a048915639d71000139f425": "eve@mtnra.com", "59b65210faeeee0001d1e60d": "worldshaper@protonmail.com", "59b653785a8b5b00013113b6": "jerome@constructivesolutions.com.au", "59b651090edf79000135da65": "pedrobfarias@gmail.com", "59b651b75a8b5b0001311332": "openrouteservice.org@michael-prokop.at", "5a2436a87b75940001a3dcc4": "nick@nickbloom.co.uk", "59f41e335c524200016c9be1": "dragandjordjevic@hotmail.com", "59cb3a9621f54a0001e0c47a": "rotemhai@gmail.com", "59d912a851f60100011f1fe1": "y_kasav1@hotmail.com", "59b65321e3567a0001d9bef9": "fred.trott@gmx.de", "59b654a7e3567a0001d9bf64": "proyectoatalaya@outlook.es", "59b652370edf79000135daad": "markus.bergelt@gmail.com", "59b651cd5a8b5b0001311336": "cynthia.devos1992@gmail.com", "59b650dadac3350001574f93": "pedro.solla@posteo.de", "59b653340edf79000135daf6": "nitzanmatan@gtmail.com", "59b651745a8b5b000131131e": "rodrigo.borlone@gmail.com", "59b652cb5a8b5b0001311384": "biaster@gmx.net", "59b65564e3567a0001d9bf94": "asmgma@gmail.com", "59c93351b87b2d0001c4f108": "stankyshoes@yahoo.com", "59f443ad7c4f2b0001f3754e": "info@alpter.eu", "59b65375e3567a0001d9bf10": "akinolamauyon@gmail.com", "59b652aae3567a0001d9bedb": "e.lauriol@cartographie-et-sig.fr", "59b6517cfaeeee0001d1e5ef": "wiesehahn.jens@gmail.com", "59b653e10edf79000135db35": "jan.dix@uni.kn", "59cfa1976f18a00001e1645d": "68r.lucas@gmail.com", "59b6519de3567a0001d9be96": "douglas.uemura@gmail.com", "59b652afe3567a0001d9bedd": "vincent_lethuillier@hotmail.fr", "59b655ade782050001d67176": "scharwar@gmx.de", "59bf9fc94d309a000199e6b3": "jochen.sandmaier@heidelberg.de", "59b652a8faeeee0001d1e63d": "alessandro.marucci@univaq.it", "59b651e45a8b5b000131133c": "carsten.rodin@gmail.com", "59b651020edf79000135da64": "lunarok@gmail.com", "59b654c15a8b5b0001311415": "chack.chen@gmail.com", "59b6523ee3567a0001d9bebb": "teddyumd@gmail.com", "59b650ffdac3350001574f9b": "martkess@gmx.de", "59b652c25a8b5b0001311380": "ew.fitzek@gmail.com", "59b65498e3567a0001d9bf62": "arnaud.mayis@aua-toulouse.org", "59b653cde3567a0001d9bf2a": "andreas.kjonsvik@trondheim.kommune.no", "59b653965a8b5b00013113be": "dkocich@gmail.com", "5a216d33dc1cc3000124ca85": "xcv04@yahoo.com", "59b651f40edf79000135da9f": "nico_sallaberry@yahoo.fr", "59b6535ae3567a0001d9bf06": "matt@wildwalks.com", "59b6555c0edf79000135db8e": "trailmakerapp@gmail.com", "59b652fee3567a0001d9bef0": "trilambda122@gmail.com", "59b652fee3567a0001d9bef1": "wout.peterse@gmail.com", "59b654320edf79000135db48": "gcoiro@gmail.com", "59b654cbfaeeee0001d1e6db": "daniel.proietti@gmail.com", "59b653fafaeeee0001d1e6a2": "q.morise@tracerlaville.fr", "59b65318e3567a0001d9bef7": "christianhof@gmx.de", "59b652e20edf79000135dad8": "paul@zoole.net", "59b6531d0edf79000135daee": "martin+test123101@tyk.io", "59b65393faeeee0001d1e67b": "tobias.coetzee@bigenafrica.com", "59b654395a8b5b00013113e9": "ruben@parcelpro.nl", "59b651e6faeeee0001d1e605": "hicharlene@gmail.com", "59b6539cfaeeee0001d1e680": "nob2575@gmail.com", "59b655c9faeeee0001d1e71a": "v.kiousis@outlook.com", "59b654d2faeeee0001d1e6dd": "gaspar.soria.eibe@gmail.com", "59b654370edf79000135db4a": "mruthyunjaya.hr@ispatialtec.com", "59b65355faeeee0001d1e66c": "malyutin.constantin@gmail.com", "59b65125e3567a0001d9be81": "philxxx609@msn.com", "59b65155e3567a0001d9be89": "arz96@yandex.ru", "5a1d55386b2cac000118de18": "walter.philipp97@t-online.de", "59b653adfaeeee0001d1e686": "n.ratti@systematica.net", "5a184fff3059880001902b23": "caricato.luca@outlook.it", "59b6536afaeeee0001d1e670": "carloschamba@gmail.com", "59b650fa0edf79000135da62": "foxfortmobile@gmail.com", "59f8becee84de100011e8837": "jsspaulding92@gmail.com", "59b6546e0edf79000135db61": "oscar.forner.martinez@gmail.com", "5a045f2d52766b00010b6f5e": "buhr@buhr-gruppe.de", "59b653760edf79000135db13": "adonaislee.urbanismo@gmail.com", "59cba3aa06be0900010482e9": "fcdonald.krenn@a1.net", "59b6531fe3567a0001d9bef8": "panos.floros@hotmail.com", "59b653585a8b5b00013113ab": "jean-sebastien.roussy@optimarketing.com", "59b6507fdac3350001574f8c": "nudtlliu@gmail.com", "59b6549b5a8b5b0001311408": "alxgrlk@gmail.com", "59b65573faeeee0001d1e707": "macleanhawley@gmail.com", "59b653530edf79000135db07": "sylwia.rudyk@straz.gda.pl", "59b65362e3567a0001d9bf09": "m.gemsa@brenner-bernard.com", "59b652fd5a8b5b0001311393": "adamjvogt@me.com", "59b654dfe782050001d67146": "sodifrance.gin@gmail.com", "59b65547e782050001d67160": "gvicente@mail.telepac.pt", "59b65203dac3350001574fd0": "daniel.schmidt2010@gmx.de", "59b654c00edf79000135db74": "eva@myhome-norderney.de", "59b6523fe3567a0001d9bebc": "r.pellicier@inddigo.com", "59b653115a8b5b0001311397": "monika.walizkazciuchami@gmail.com", "59b65365e3567a0001d9bf0b": "41050a010@ems.ndhu.edu.tw", "59b654e4e782050001d67148": "sb@xn--expressnet-yz0g.de", "59b65390faeeee0001d1e67a": "haytastan@gmail.com", "59b6535b0edf79000135db0a": "msc.minex@gmail.com", "59b653915a8b5b00013113bd": "luipir@gmail.com", "5a01c5f75994c500011b1796": "schusjul@googlemail.com", "59b652a90edf79000135dac8": "jowwa2@aol.com", "59b65201e3567a0001d9bead": "rycalvo@gmail.com", "59b654a5e782050001d67138": "just.dior@zoho.com", "59b65407e3567a0001d9bf3b": "pfn1950@gmail.com", "59b65141faeeee0001d1e5e0": "liuben.siarov@gmail.com", "59b652c6faeeee0001d1e648": "jorge.basura@gmail.com", "5a1b7358f0a16100010f63dd": "vul2824@gmail.com", "59b655c25a8b5b0001311445": "horaciojimenez@gmail.com", "59b6515e0edf79000135da7b": "edanweis@gmail.com", "59b654e6e3567a0001d9bf73": "itaiwanbike@gmail.com", "59b654925a8b5b0001311406": "jef.maas@telenet.be", "59b650795a8b5b00013112f9": "bosag1987@yahoo.com", "59b6518ffaeeee0001d1e5f4": "marcin@staniszczak.pl", "59b654270edf79000135db44": "stefan.prinz@ifmpt.de", "59b654ac5a8b5b000131140f": "henrique.melissopoulos@gmail.com", "59b6535e0edf79000135db0b": "sauyu4426@gmail.com", "59f20008b8125f0001376a59": "b.bundtzen@web.de", "59b655905a8b5b0001311438": "notruepd@gmail.com", "59b65284e3567a0001d9bece": "huubmetz@onsnet.nu", "59b6545d5a8b5b00013113f6": "info@etslife.eu", "59b654b1e3567a0001d9bf67": "CYNTHIAMATTA18@GMAIL.COM", "59d7517bb8125f00013766ef": "klaus.hanauer@t-online.de", "59b650ebdac3350001574f96": "johnf@dezza.net", "59b65288e3567a0001d9becf": "thomas.wagner@apa.at", "59b652f70edf79000135dae1": "alice.noyce-mead@quod.com", "59b654670edf79000135db5f": "stefano.campus@regione.piemonte.it", "59b651220edf79000135da6b": "gsnowball@rsk.co.uk", "59b655afe782050001d67177": "h.omg@web.de", "59b652250edf79000135daa7": "rushharris@marshalledc.org", "59b654c75a8b5b0001311417": "marco.menchise@gmail.com", "59b653a6faeeee0001d1e683": "mail@tiefengrad.de", "5a1fc0c39b751c00018ffd4b": "lara.hanau98@gmail.com", "59b65303faeeee0001d1e659": "bartosek.petr@gmail.com", "5a2a6fa8b0d310000122e1fe": "jens.lochmann@rpgls.brandenburg.de", "59b650eee3567a0001d9be71": "carlosvquezada@yahoo.com", "59b6521bfaeeee0001d1e612": "r.lievers@2image.nl", "59b651fe0edf79000135daa0": "ivan@corkchamber.ie", "59b653a40edf79000135db21": "serzant@gmx.de", "59b655ace3567a0001d9bfa0": "sjpark1989@gmail.com", "59b654c4e3567a0001d9bf6b": "remco.veltrop@ipsoft.com", "59b652c90edf79000135dad1": "kevin@kevinsterckx.be", "59b651850edf79000135da84": "jonashenkhaus@gmail.com", "59def599693d9f00018fc530": "Claudia.Fuhrmann@partner.kit.edu", "59b655c0e782050001d6717a": "t.lesceller@vizea.fr", "59b6517ae3567a0001d9be90": "u214892@sbb.ch", "59b65533e782050001d6715c": "m.teunissen@zorggroepsez.nl", "59b6544de3567a0001d9bf50": "zanardo.mauro@gmail.com", "59cdef58a778190001e225c0": "pepe@ibm.com", "59b655925a8b5b0001311439": "mfaisal.razali@gmail.com", "59b65501e3567a0001d9bf7a": "ptisca@live.fr", "59b6548d0edf79000135db69": "ferreira.harlan@gmail.com", "59b651d1e3567a0001d9bea3": "dariusz.b@gmail.com", "59e0cc9e09c47100010d13b5": "mail@markus-gonzalez.de", "59b65245e3567a0001d9bebf": "peters@chadoteahouse.com", "59b65418faeeee0001d1e6ab": "angelo.zinnai@gmail.com", "59b65242e3567a0001d9bebd": "jules@yopmail.com", "59ff0201419e770001184cc7": "moritz.boese@gmx.de", "59b653f2faeeee0001d1e69f": "chost@agd.com.ar", "59b65525e782050001d6715a": "etiennerobillard@hotmail.com", "59b65577e782050001d6716b": "anar.jismayilov@gmail.com", "59b652a55a8b5b0001311379": "ildoshallas@yahoo.com", "59b654835a8b5b0001311403": "eric.smets@fks.be", "59b653dbe3567a0001d9bf2e": "roland.bryant@yardi.com", "59b65461faeeee0001d1e6b9": "tammy@littlechutewi.org", "59b652205a8b5b000131134f": "siafu@mail.ru", "59b653c9e3567a0001d9bf29": "eugene@propertyeconomics.co.nz", "59b65214e3567a0001d9beb2": "jmamuedo@gmail.com", "59b65178faeeee0001d1e5ed": "jwimpey@worldbank.org", "59b65558faeeee0001d1e702": "cain.arbiter@aimlio.com", "59b654f80edf79000135db7a": "johannesm.reiss@web.de", "59b65510faeeee0001d1e6eb": "Grant.Hanham@nra.health.nz", "59b65304e3567a0001d9bef3": "brianadr@optusnet.com.au", "59fdf1e8144ad1000197c513": "b.krahl@gmx.de", "59b6525efaeeee0001d1e626": "estefanie.zollmann@gmail.com", "59b653c1e3567a0001d9bf27": "takadoumimarwane@gmail.com", "59f09409105fb100010d5ee8": "elisabeth.henriet@unamur.be", "59b653b50edf79000135db25": "info@gehr-gmbh.de", "59b65484faeeee0001d1e6c7": "heijnki@googlemail.com", "59b653b1e3567a0001d9bf22": "dharmendra1983@gmail.com", "59b652365a8b5b0001311359": "thomas.wiederkehr@ls.kv.bwl.de", "59b652eb5a8b5b000131138d": "christophe.anselmo@gmail.com", "59b65312faeeee0001d1e65d": "daniele.moggia@gmail.com", "59b651dbe3567a0001d9bea5": "sprabakaran@chn.aithent.com", "59b6518a0edf79000135da85": "jri@rvmk.nl", "59b655030edf79000135db7d": "jgozdek@transportinsights.com", "59b651f9dac3350001574fcc": "chenmu.derek@gmail.com", "59b6550de782050001d67151": "bahmanshams@live.com", "59b654a85a8b5b000131140e": "juanjose@erazo.mx", "59b652b15a8b5b000131137c": "tom.vandevoorde@ordina.be", "59e4c2d3b8125f0001376896": "antoine.rayssiguier@ensg.eu", "59b651430edf79000135da73": "marcel.ibold@outlook.com", "59b652fffaeeee0001d1e658": "illya.sparkes.santos@gmail.com", "59b651b5dac3350001574fbc": "jturner@bpu.com", "59b6537ffaeeee0001d1e674": "eros85@gmail.com", "59b65107faeeee0001d1e5cd": "dev.sfullez@gmail.com", "59b6551f0edf79000135db81": "henning.lorenz@geo.uu.se", "5a266bb08a8b820001b8e434": "stewk@web.de", "59b655b15a8b5b0001311442": "mcallisterw@gmail.com", "59d6785635b37c00017b2563": "olaf.wichmann@aol.de", "5a1821a5bb7f67000110435a": "xenia.kopf@gmail.com", "59b651efe3567a0001d9beab": "heif-elem@hotmail.fr", "59b653be0edf79000135db28": "andreas.roshop@ewe.net", "59b6534f0edf79000135db05": "a.rehak@gmx.net", "59da5f2007e1620001491b24": "rameva-1976@hotmail.es", "59b651af0edf79000135da8f": "steven.brownstone@idinsight.org", "59b65255faeeee0001d1e624": "igau.pierre-damien@cegetel.net", "5a1c117ecb84e2000186b963": "dirk.hering@castrop-rauxel.de", "59ede1ab38b8aa0001b39ccf": "admfarias@gmail.com", "59b655610edf79000135db8f": "rglauber83@gmail.com", "59b6540ffaeeee0001d1e6a7": "valentin_muller@outlook.fr", "59b651c8faeeee0001d1e5fe": "rochmat.setiono@acsata.com", "59b652785a8b5b000131136a": "porlo@citadia.com", "59b652defaeeee0001d1e650": "JimRitter@aol.com", "59b655bde782050001d67179": "fhjdhjfdg@djhfbfd.com", "59b654d4e782050001d67142": "vini@revvidmedia.com", "59b654ade3567a0001d9bf65": "johannes.schwer@geo.uni-augsburg.de", "59b812cb3a0d1a00013b66d1": "erannoux@gmail.com", "59b65151faeeee0001d1e5e2": "marco.teixeira@globaleda.pt", "59b652525a8b5b0001311362": "evelim.estrada@gmail.com", "59b654ece3567a0001d9bf74": "eligehausen@uni-kassel.de", "59b6526f0edf79000135dab8": "paul.ashforth@gmail.com", "59b65148dac3350001574fa7": "artonge.c@gmail.com", "59b6532e5a8b5b00013113a1": "geobernadotte@googlemail.com", "59b65136dac3350001574fa4": "morgan44@hotmail.de", "59b6553dfaeeee0001d1e6fa": "radzios@gmail.com", "59b6524e5a8b5b0001311360": "kevin.hendricks@dynamicpeople.com", "59b6552a0edf79000135db82": "williampwak@gmail.com", "59b6539ee3567a0001d9bf1d": "girobusan@gmail.com", "59c174988608600001dfef2e": "alessandroregio@gmail.com", "59b651975a8b5b0001311328": "matthias.plennert@fau.de", "59b6525a5a8b5b0001311363": "lefernandes.h@gmail.com", "59b651e1dac3350001574fc4": "adityaprandhana@gmail.com", "59b654250edf79000135db43": "xiaolei.zhang@tc-systeme.com", "59f7956a338ef50001113d1c": "thoommas35@gmail.com", "59b652cf0edf79000135dad3": "boris@agencerybal.com", "59b654f0e3567a0001d9bf76": "david.campoy@airnetwifi.es", "59b653310edf79000135daf5": "hubackova.lenka@gmail.com", "59b654c6e3567a0001d9bf6c": "dpelinkow@gmail.com", "59b651570edf79000135da79": "projetos.ceara@gmail.com", "59b65194e3567a0001d9be94": "9237010177@mail.ru", "59b65291e3567a0001d9bed2": "franciscogutierrez737@gmail.com", "59b6555be3567a0001d9bf91": "hsi@112interreg.eu", "59b65153dac3350001574fab": "llong@santafe.gov.ar", "59fdb41f144ad1000197c50b": "Annina.Herrmann@gmx.de", "59b6f42108174700016d2bae": "saikrushnu@gmail.com", "59b65535e3567a0001d9bf8a": "clanchon@even-conseil.com", "59b65289faeeee0001d1e637": "mail@jonas-wendler.de", "59b6544b5a8b5b00013113ee": "info@brouwerinbeeld.nl", "59b653880edf79000135db19": "eccentricpilgrim@gmail.com", "59b653e3faeeee0001d1e698": "katy.leduc@live.fr", "59b6555ee3567a0001d9bf92": "remi.moussac@gmail.com", "59b655bce782050001d67178": "michael.obrien@ul.ie", "59b653ebfaeeee0001d1e69c": "cortes.yasna@gmail.com", "59b655d1e782050001d6717e": "bo.steadman@hines.com", "59b652f2e3567a0001d9beec": "ncliam@yahoo.com", "59b652e40edf79000135dad9": "i.kuijer@tfe.nl", "59b65540e3567a0001d9bf8c": "cpalomino@uach.mx", "59b6508f0edf79000135da58": "asim@signature-design.co.uk", "59b651920edf79000135da88": "biuro@dron4all.pl", "59b651a60edf79000135da8e": "ronya.reitberger@gmail.com", "59b654705a8b5b00013113fd": "nguyenvantuongcsek14@gmail.com", "59e8aeace0120e00016b5cd9": "klaus.peter.hurtig@gmail.com", "59b654705a8b5b00013113fc": "yasugi.nds@gmail.com", "59b6537de3567a0001d9bf13": "vadim.chadyuk@gmail.com", "59b6515c5a8b5b000131131c": "rschnickmann@gmail.com", "59b654340edf79000135db49": "anthony.chaput@etu.univ-lyon1.fr", "59b6530d0edf79000135dae9": "jean-baptiste@easy-mountain.com", "59b65405e3567a0001d9bf3a": "mehmet.girtten@reutlingen.de", "59b654100edf79000135db40": "atchombena@gmail.com", "5a27ebf974e05c00013704ea": "martina.galasso93@gmail.com", "59b653195a8b5b000131139a": "felixbublitz@googlemail.com", "59b652eefaeeee0001d1e653": "marhs@vejle.dk", "59b6511f5a8b5b000131130c": "benderlio@gmail.com", "59b6511f5a8b5b000131130b": "nick.marinella@gmail.com", "59b65349e3567a0001d9bf03": "julia.kuner@gmx.de", "59b65163faeeee0001d1e5e7": "igor.litrop@elmitel.com", "59b654140edf79000135db41": "ernesto.carreras@gmail.com", "59b654580edf79000135db59": "rafiq10@gmail.com", "59b651fb5a8b5b0001311344": "stuart.trentham@rfl.co.uk", "59b653865a8b5b00013113b9": "ssurampudi@gmail.com", "59c375372901350001d4178d": "office@hyperworx.de", "59b6523ae3567a0001d9beba": "krzysiek2005_1983@o2.pl", "59b653920edf79000135db1c": "olivier.mamdy@bas-rhin.fr", "59b65281faeeee0001d1e634": "eyarkoni@gmail.com", "59d1ae1c0041550001c6f01c": "darrylheadley25@platinum.iskba.com", "59b650d75a8b5b00013112ff": "dan000roller@gmail.com", "59b654abfaeeee0001d1e6d3": "murwira@gis.uz.ac.zw", "59b655cb5a8b5b0001311446": "fernando_irarrazaval@hks18.harvard.edu", "59dd322d871b580001829fbe": "pointsnorthgis@gmail.com", "59b653fbe3567a0001d9bf38": "georg.weickelt@ibedelmann.de", "59b654710edf79000135db62": "romain.raffin@lsis.org", "59dd9b24a080af0001dccd7a": "eesqjz7@220w.net", "59b65217faeeee0001d1e610": "mrgolshan@yahoo.com", "59b6558afaeeee0001d1e709": "s0555625@htw-berlin.de", "59b652325a8b5b0001311357": "gstoberl@gmail.com", "59b6538ce3567a0001d9bf18": "andrew10642@gmail.com", "59b651c7dac3350001574fbe": "b.hendrikx2@gmail.com", "59b651c7dac3350001574fbf": "j_rodriguez_arruela@hotmail.com", "59b65595e782050001d67170": "majdadyr@gmail.com", "59c61d576070ca0001f62a3c": "snick76@gmx.de", "59b653e2e3567a0001d9bf32": "hejjazy@ymail.com", "59b653f4faeeee0001d1e6a0": "marcio.vicenteluis@gmail.com", "59b651e70edf79000135da9d": "buchelnikov@amedia-network.ru", "59b651b25a8b5b0001311330": "portal@geoceane.fr", "59b652ce0edf79000135dad2": "info2@ad-ip.eu", "59b654aee3567a0001d9bf66": "bigblacklazycat@gmail.com", "59b652e1e3567a0001d9beea": "e.n.bespalova@gmail.com", "59b653c6faeeee0001d1e690": "smercier@mapgears.com", "59b652095a8b5b0001311346": "zyru30@gmail.com", "59b653a1faeeee0001d1e682": "sig@siaepavi.fr", "59b651e50edf79000135da9c": "christian.wolff@hs-anhalt.de", "5a0f525c17f6440001d71929": "Sian23sian@gmail.com", "59b653740edf79000135db12": "joselbarradas88@gmail.com", "59b6551de782050001d67156": "gaurav.sahu13211@gmail.com", "5a0af00664c3b40001536f1f": "joerg_wendt@gmx.de", "59b654640edf79000135db5e": "cesarfernando.11@gmail.com", "59b6554afaeeee0001d1e6fe": "zach@y3m.net", "5a01b46d8f7e110001c6ada6": "julianahreczuck@gmail.com", "59b654b75a8b5b0001311411": "kandler@gc-i.de", "59b655b2faeeee0001d1e712": "meiqing@upenn.edu", "59b65167faeeee0001d1e5e8": "sig@creusot-montceau.org", "59b65524faeeee0001d1e6f2": "gundelino85@gmail.com", "59b653b20edf79000135db24": "armyguy62@gmail.com", "59b6527be3567a0001d9becc": "dominikjanernst@hotmail.de", "59b652b1e3567a0001d9bede": "will@wiljaxon.net", "59b654f1faeeee0001d1e6e6": "turcsan.adam@legow.hu", "59b6516b0edf79000135da7d": "john.carotta@state.ca.gov", "5a01b2be3140460001f061ba": "demmer@servario-networks.de", "59b65324e3567a0001d9befa": "saleemahisham@gmail.com", "59b6512c0edf79000135da6c": "icq4ever@gmail.com", "59b655005a8b5b0001311421": "allanw@slalom.com", "59b652f1faeeee0001d1e654": "andreacardoso98@yahoo.com.br", "5a0e041b25af590001b10fac": "maragon@cuenca.es", "59b65567faeeee0001d1e705": "darioz@tiscali.it", "59b6521d5a8b5b000131134d": "peut.w17@gmail.com", "59b654f2e3567a0001d9bf77": "ckohler4692@gmail.com", "5a0b2408723872000126a308": "spred@blueyonder.co.uk", "59b654aa0edf79000135db6f": "juane.nunez@epresa.com", "59b655cafaeeee0001d1e71c": "yasmin.howell@glyndebourne.com", "59b65206faeeee0001d1e60c": "leldin@epfif.fr", "59dceacb1fa05c00015c22cd": "rein.dat@gmail.com", "59b650c70edf79000135da5b": "ben@imcal.la", "59b654fb5a8b5b000131141f": "gis@int.pl", "59b651bc0edf79000135da94": "hej@urland.dk", "59b651ca0edf79000135da97": "beldin18@gmail.com", "59d4fbae82f2000001f7140e": "casper.pasveer@gmail.com", "59b651c40edf79000135da96": "Werner.Maus@post.rwth-aachen.de", "59b653c10edf79000135db2a": "giuseppe.geloso.f9r8@alice.it", "59b653b2e3567a0001d9bf23": "bruno.dauwe@actemium.com", "5a22e6d88c3a2a000113bffc": "vganeshan@gmail.com", "59b6524ffaeeee0001d1e620": "foscone@gmail.com", "59b655c6e3567a0001d9bfa5": "v.skrebtsov@mail.ru", "59b652fc5a8b5b0001311392": "andrea.de.mauro@uniroma2.it", "59b65544e782050001d6715f": "bradfordsteven91@gmail.com", "59b65127faeeee0001d1e5d5": "zhupy2013@gmail.com", "59b6545b0edf79000135db5a": "26905712@qq.com", "59b654fc5a8b5b0001311420": "gefische@freenet.de", "59b9113c6070ca0001f6289d": "paul.barker@hartlepool.gov.uk", "59b6533a0edf79000135dafa": "aoxtoc@web.de", "59b651f20edf79000135da9e": "doniecasey@gmail.com", "59b655870edf79000135db95": "info@nexgenbroadband.com", "59b65276faeeee0001d1e632": "d.kantor@mito.hu", "59b654cce782050001d6713e": "paul.stanley@cabbytech.com", "59b652f60edf79000135dae0": "pawel.dudek@assecobs.pl", "59b6558f5a8b5b0001311437": "havran@gmail.com", "59b655c30edf79000135dba0": "n3u3w3lt.work@yandex.ru", "59b651ac5a8b5b000131132e": "nuevo@luxspace.lu", "5a2e9db286af6f0001e5e8d4": "anna.korpinen@sitowise.com", "59b655c80edf79000135dba2": "finalpriest@hotmail.com", "59b65123faeeee0001d1e5d3": "marion.lacombe@lineamenta.fr", "59b652f35a8b5b000131138f": "l.tielkes@web.de", "59b651be5a8b5b0001311333": "christian.mosblech@prismat.de", "59b650dde3567a0001d9be6f": "nik.chelny@gmail.com", "59b651085a8b5b0001311308": "johannes.schneider@student.hpi.de", "59b65319faeeee0001d1e660": "melonsw@gmail.com", "59b655c1e3567a0001d9bfa4": "eganahl@web.de", "59b655c1e3567a0001d9bfa3": "vertax@mail.ru", "59b654bafaeeee0001d1e6d7": "zapa@seznam.cz", "59b65293e3567a0001d9bed3": "aira@posteo.net", "59b65293e3567a0001d9bed4": "johannes.lieberherr@ttools.ch", "59b6534ce3567a0001d9bf04": "matthew.lee@deependservices.com.au", "59b651805a8b5b0001311320": "jamiro.it@gmail.com", "59b65112faeeee0001d1e5cf": "herr.schuster@gmx.at", "59b654b2faeeee0001d1e6d5": "daniel.sebastian.karla@students.hs-mainz.de", "59b6550c5a8b5b0001311423": "schrall@schrall.com", "59b65202faeeee0001d1e60a": "curtis.mack@lgan.com", "59b655140edf79000135db80": "robert.shaw4@nhs.net", "59b6507cdac3350001574f8b": "ulrich.lang@swr.de", "59b6540e5a8b5b00013113db": "dbarbalatt@partnereconomics.com.au", "59b6518dfaeeee0001d1e5f3": "nozdrin@l-39.aero", "59b654fb0edf79000135db7b": "yves.cordier@telenet.be", "59b651475a8b5b0001311316": "halo314@gmail.com", "59b94e1b3927a10001520568": "nitsuga@pobox.com", "59b6549f5a8b5b000131140b": "phrakornkham.joey@gmail.com", "59cb68fd21f54a0001e0c482": "leon.ziesing@googlemail.com", "59b651a20edf79000135da8b": "cmgraham@me.com", "59b651a20edf79000135da8c": "online.matsuo@gmail.com", "5a152a51c0ae4200019fb643": "charles.billau@gmail.com", "5a153273c0ae4200019fb644": "valeriemanin92000@gmail.com", "59b655310edf79000135db85": "jromeroausin@gmail.com", "59b6529b0edf79000135dac5": "alfredo.polo@mac.com", "59b6529cfaeeee0001d1e63c": "petter.hultin@laketide.com", "59b6512ffaeeee0001d1e5da": "planetizen@gmail.com", "59b653360edf79000135daf7": "alvaro.barbero@iic.uam.es", "59b6515ae3567a0001d9be8b": "dan.jamara@modolabs.com", "59b654900edf79000135db6a": "monica82villegas@gmail.com", "59b65292faeeee0001d1e63a": "politicametrics@gmail.com", "59b6532ae3567a0001d9befb": "nguyenhoanghai2808@gmail.com", "59b6548c5a8b5b0001311404": "tiphaine.lbg@gmail.com", "59b653b8e3567a0001d9bf25": "seyibangbe@gmail.com", "59b6552de3567a0001d9bf87": "slaveg_1996@mail.ru", "59b653075a8b5b0001311395": "vivek@crystalhr.co.in", "59b65357faeeee0001d1e66d": "admin@fractale.xyz", "59b654305a8b5b00013113e6": "info@hhemmer.de", "59b6539ffaeeee0001d1e681": "sspinks@pellfrischmann.com", "59b652b9e3567a0001d9bedf": "benjamin.willig@gmail.com", "5a265994db1d150001c1b618": "thomas-stalinski@t-online.de", "59b655cdfaeeee0001d1e71d": "VERONICA.GABUSI@GMAIL.COM", "59b6535fe3567a0001d9bf07": "410203005@gms.ndhu.edu.tw", "59b653a2e3567a0001d9bf1e": "ks255@st-andrews.ac.uk", "59b650ec0edf79000135da5f": "richard.veit@Capita.co.uk", "59b651dee3567a0001d9bea7": "sgurbinder858@gmil.com", "59b65379faeeee0001d1e673": "mohit@bigbinary.com", "59b654bd5a8b5b0001311414": "martin.uebelhoer@lehenhof.de", "59d42de9191623000154882e": "javier.gonzalez@conaf.cl", "59b654b85a8b5b0001311412": "nils.wolffram@dbl-zentrale.com", "59b65352faeeee0001d1e66b": "nissen_the@hotmail.com", "59b6544c0edf79000135db55": "juda.olivier@gmail.com", "59b655175a8b5b0001311425": "michele.spinella@corvallis.it", "59b654c1e782050001d6713c": "ralf.jungmann@mitternachtslaeufer.de", "59f0b0ee28890b0001d633e9": "mliulion@gmail.com", "59b655a10edf79000135db99": "zellerfeld@yahoo.de", "5a1457d9bb83c400016cfb80": "gabevin@gmail.com", "59b6520f5a8b5b000131134a": "mailboxdejared@gmail.com", "59b651845a8b5b0001311322": "ngui.michel@live.fr", "5a12e278559cf300014bd249": "gilbert.helwich@gmail.com", "59b65518e782050001d67154": "cnegron@temagc.com", "59b6546ffaeeee0001d1e6c0": "alexfanfa@gmail.com", "59b655745a8b5b0001311434": "slynde@es-and-c.com", "59b650a00edf79000135da59": "hosein.madadi@gmail.com", "59b651fa5a8b5b0001311343": "ensnared@gmail.com", "5a2ef074e3fbf30001f46142": "safaaaaaaa@hotmail.fr", "59b653510edf79000135db06": "willem@mandalagis.co.za", "59b6512a5a8b5b000131130f": "zimedel@hotmail.com", "59e766d2cbddb50001d5e1fe": "philipp.hessemer@stadt-koeln.de", "59b654625a8b5b00013113f8": "a.glowa@interia.eu", "59b653a9e3567a0001d9bf21": "kikill1123@yahoo.com.tw", "59ece8feeb1b680001e88853": "fuellekr@gmail.com", "59b654045a8b5b00013113d7": "gis.bkf@odense.dk", "5a1dd2e0ec4e750001a28da5": "herenkovics95@gmail.com", "59b6546afaeeee0001d1e6be": "cronos8989@gmail.com", "59b65117e3567a0001d9be7e": "bot@nemunai.re", "59b652750edf79000135dabc": "hjt_elephant@163.com", "59ffa0bb8017c80001fa2ef2": "efef@free.fr", "5a1a6da9747a5d00018d2d6c": "pha9t1m@yandex.ru", "59b65447faeeee0001d1e6b3": "afz9376@163.com", "59b652a45a8b5b0001311378": "j.d.mutsters@home.nl", "59f46fe8b8125f0001376a89": "gsboxertreiber@gmail.com", "59b6529f5a8b5b0001311375": "gerson92_12@hotmail.com", "59b6549efaeeee0001d1e6cf": "pascal_vorhaus@mckinsey.com", "59b652e0e3567a0001d9bee9": "ahloy04@gmail.com", "59b651b40edf79000135da91": "office@congruent.at", "5a038a4692419d000198d799": "corentinlemaitre@gmail.com", "5a1b73eb7cd6870001d39b37": "range87514@gmail.com", "59b65062e3567a0001d9be6b": "salla_masyon@hotmail.com", "59b65487e3567a0001d9bf5c": "richard.grasse@bkg.bund.de", "59b652f35a8b5b0001311390": "h.dietrich@nabu-umweltpyramide.de", "59b650fce3567a0001d9be73": "pillisan42@gmail.com", "59b653a30edf79000135db20": "brauer@faktor-e.de", "59b6511cfaeeee0001d1e5d2": "enviro@oviwc.com", "59b651b7faeeee0001d1e5fa": "immonews.ma@gmail.com", "59b6530c0edf79000135dae8": "Ana-Maria.Boar@cegeka.com", "59b6537b5a8b5b00013113b7": "pierre.alix@yandex.com", "59b651aee3567a0001d9be9b": "hjenkins@gasbarre.com", "59b654415a8b5b00013113ec": "inscription@clement-audebert.fr", "59b6518b0edf79000135da86": "antonin.vorkaufer@eifer.org", "5a0c8280a6979300014fd52f": "antoine.perron@moba-cgd.com", "5a071c2137f97300010dee2a": "d93521009@ntu.edu.tw", "59b650f1faeeee0001d1e5ca": "erickdiaz9@gmail.com", "59b65475faeeee0001d1e6c2": "moreau.carto@wanadoo.fr", "59b653f70edf79000135db3c": "ganeshr@imtac.com", "59b65205faeeee0001d1e60b": "m.rogge@ebusplan.com", "59b653f85a8b5b00013113d0": "rolf.klingel@googlemail.com", "59b65338e3567a0001d9befe": "gastenkamer@gmail.com", "59b6522ae3567a0001d9beb5": "joaol@sentilant.com", "59b652dde3567a0001d9bee7": "mcostilla@gotablanca.com.mx", "59b6545e5a8b5b00013113f7": "guillerm.yann@wanadoo.fr", "59b651e9dac3350001574fc6": "w.beijeman@live.nl", "59f32817b8125f0001376a7a": "marcel.prehn@acando.de", "59b651a7dac3350001574fba": "axel1991@hotmail.de", "59b654ca0edf79000135db75": "matthias.schaffer@ffgallneukirchen.at", "59d49d8673529b000106495b": "friedrich.pfeffer@web.de", "59b650afdac3350001574f90": "nils.nolde@zalando.de", "59b650ed5a8b5b0001311302": "c_kozubowski@hotmail.com", "59b654b6e782050001d67139": "j.sanjose@planed.fr", "59b6528a0edf79000135dac1": "morgan.reece@bartonwillmore.co.uk", "59c20e700d24870001a0ce29": "f.gill@4-go.de", "59b6554b5a8b5b000131142d": "andreaslauer90@googlemail.com", "59f3b425f92aff00017388c1": "puppyurvee@gmail.com", "59b65254faeeee0001d1e623": "idwabo@gmail.com", "59b651f35a8b5b0001311340": "elseewolf@googlemail.com", "59e34d3469bddc0001c9340d": "1231380@uni-wuppertal.de", "59e48f1ad1085900012317db": "catherine.white@cumbria.gov.uk", "59b653d90edf79000135db32": "chris.nall87@googlemail.com", "5a09bdf664459d000127d02f": "r3178796@mvrht.net", "59c02381099a360001b6f8f4": "georgeme007@gmail.com", "59b653b35a8b5b00013113c3": "julian.bettermann@gmail.com", "59b65579e782050001d6716c": "sergeypavlov.yu@gmail.com", "59b651445a8b5b0001311315": "juanma2413@gmail.com", "59b65267faeeee0001d1e62a": "am@dialoghaus.com", "59b652b25a8b5b000131137d": "hableconleo@gmail.com", "59b653440edf79000135daff": "olehmkuhl@uni-osnabrueck.de", "59b65215faeeee0001d1e60f": "shenhao@cuc.edu.cn", "59b652e55a8b5b000131138b": "mohammed.nabil@gmail.com", "5a116f6bcaf1e70001825ae1": "amarocks9@gmail.com", "59b6554fe3567a0001d9bf8f": "julian.schoebel@smail.th-koeln.de", "59b65361faeeee0001d1e66f": "ingrid.fossum@roros.kommune.no", "5a0953366cb82f0001678c97": "mbh.map@gmail.com", "59b651405a8b5b0001311314": "teschj@gmx.at", "59b6559fe3567a0001d9bf9d": "admin@flightsurvey.com", "59b652eae3567a0001d9beeb": "jaroslav_merenkov@mail.ru", "59b652135a8b5b000131134b": "ann@annsharrock.com", "59b6559dfaeeee0001d1e70c": "info@banar.de", "59b6559dfaeeee0001d1e70d": "victor.antunes72@gmail.com", "59e9a011395b160001e382e8": "paumjust@hotmail.com", "59e701e637bda90001dfad6d": "josselin.garau-figueres@cd66.fr", "59b654fee782050001d6714f": "kwadzo459@gmail.com", "59b6531ffaeeee0001d1e662": "test@tyk.io", "59cb5c0d21f54a0001e0c47d": "stadler_reini@yahoo.com", "59b6522d5a8b5b0001311355": "tapsson@gmail.com", "59b654540edf79000135db58": "maagallanes@gmail.com", "59b653b0faeeee0001d1e688": "dirk.hargesheimer@landau.de", "59b654d3faeeee0001d1e6de": "p.meinvielle@gmail.com", "59b654470edf79000135db54": "pascal.violamer@presse-portage.fr", "59b653c3faeeee0001d1e68e": "ors@poenighaus.com", "59b654c3faeeee0001d1e6d8": "djoerd.giscovery@gmail.com", "5a0438892ad05d0001d6b4b9": "maurizio.nole@118basilicata.it", "59b655b8faeeee0001d1e715": "e.wilke@jb.de", "5a1b738ef0a16100010f63e0": "qwe21as34@gmail.com", "59b6511adac3350001574f9f": "mpfriesen@gmail.com", "59b6521efaeeee0001d1e614": "pierre.florin@kisio.org", "5a17a45cd676db0001bd5729": "nadolnygabriela@gmail.com", "59b65556e782050001d67164": "imcelwee7@gmail.com", "59b655abe3567a0001d9bf9f": "antoine.rayssiguier@wanadoo.fr", "59b654b4e3567a0001d9bf68": "yahyaq93@gmail.com", "59b65320faeeee0001d1e663": "ldg@balk.dk", "59b653de0edf79000135db34": "scott@pep.id.au", "59b655aefaeeee0001d1e711": "luke@lukewh.com", "59b6526c0edf79000135dab7": "ferizi@gmail.com", "59b654165a8b5b00013113dd": "alexhersfeldt@gmail.com", "59b651a1dac3350001574fb9": "przem.lis77@gmail.com", "59b650f95a8b5b0001311304": "m.decroos@pandora.be", "5a1c0e81cb84e2000186b961": "jvp@tbst.dk", "59b65172e3567a0001d9be8d": "lasse.setre@jernbanedirektoratet.no", "59b6553f5a8b5b000131142b": "esd@tenso-m.ru", "5a040c7979427d000154be72": "sportsinn@email.de", "59b653f5e3567a0001d9bf36": "marcovarlez@hotmail.com", "59b655975a8b5b000131143b": "adam.karolewski@raben-group.com", "59b654fafaeeee0001d1e6e8": "marcin6@gmail.com", "59b6536be3567a0001d9bf0c": "adonis.k@gmx.net", "59b651215a8b5b000131130d": "tmanev@gmail.com", "59dfc55bb8125f0001376806": "geronimo.felici@yahoo.it", "59b6518c5a8b5b0001311324": "valteralbino@gmail.com", "59f307cf2f6bc400016ed45c": "sereina.steiner@lu.ch", "59b65341e3567a0001d9bf00": "guido.bonin@gmail.com", "59b652e9faeeee0001d1e652": "fazilmuammar007@gmail.com", "59b655265a8b5b0001311428": "imad.bouhadan@student.uantwerpen.be", "59b65575e3567a0001d9bf98": "daniele.conca@cnhind.com", "59b6521ae3567a0001d9beb3": "roper.william@gmail.com", "59b653f6e3567a0001d9bf37": "adolfo.arranz@gmail.com", "59b653ef5a8b5b00013113ce": "osm@breizhpositive.bzh", "59b651eadac3350001574fc7": "info@content-provider.ch", "59b65290faeeee0001d1e639": "teste@teste.com.br", "59b653265a8b5b000131139d": "naveen.karuthedath@gmail.com", "59b653550edf79000135db09": "mancusoandrea@gmail.com", "59b6519cfaeeee0001d1e5f6": "book@onearchitecture.nl", "59b65494faeeee0001d1e6cd": "sine.gustavsen@lesja.kommune.no", "59b65468faeeee0001d1e6bc": "jgomes@nashpartnership.com", "59b652dfe3567a0001d9bee8": "collins@wapa.gov", "59b6537a0edf79000135db14": "to_alint@yahoo.com", "59b655c50edf79000135dba1": "wduan1988@gmail.com", "59b654d6e782050001d67143": "omidiporm@gmail.com", "59b654b30edf79000135db71": "max@monstermax.net", "5a035a4e24f3c900014ccc5a": "benni2407@web.de", "59b651685a8b5b000131131d": "cortizas@gmail.com", "59b652c7faeeee0001d1e649": "bene@embedded-projects.net", "59ff34f66c24e400018a60d1": "luca.roemers@gmx.de", "59b6520c0edf79000135daa3": "tmartin3@worldbank.org", "59b655a30edf79000135db9a": "jimgleeson@gmail.com", "59b653d30edf79000135db2f": "thegt4@hotmail.com", "59b6522b0edf79000135daaa": "eve.schibber@gmail.com", "5a1c0fbac136d60001d90255": "test2131415161@gmail.com", "59b652d20edf79000135dad5": "andrew.lucas@propad.com.au", "59b651abdac3350001574fbb": "slavas@bk.ru", "59b653ce5a8b5b00013113c9": "post@tinorueb.de", "59b651f5faeeee0001d1e609": "y2jasonhk@yahoo.com.hk", "59b65394faeeee0001d1e67c": "mario.stifter@dataformers.at", "59b65472faeeee0001d1e6c1": "guillaume.arias@orange.com", "59b651d0faeeee0001d1e5ff": "dex.stpierre@gmail.com", "59b65148faeeee0001d1e5e1": "steel.ricciotti@gmail.com", "5a055de6ab65210001674208": "thomas.daginnus@t-online.de", "59b651a55a8b5b000131132c": "badlinkin@web.de", "59b652a25a8b5b0001311377": "simental.law@gmail.com", "59b651fcdac3350001574fcd": "thomas.ailhaud@sdis83.fr", "59b653fe0edf79000135db3e": "miroshnichenkoa@bk.ru", "59b6559b5a8b5b000131143c": "mailrcmantri@gmail.com", "59b65144e3567a0001d9be87": "owe.achmad@yahoo.com", "59b653250edf79000135daf1": "nitaj1996@gmail.com", "59b6519cdac3350001574fb8": "pajot.bastien@orne.fr", "59b653630edf79000135db0d": "g.scarselli@publiacqua.it", "59b652dcfaeeee0001d1e64f": "mateuszjuzyszyn@gmail.com", "59ed93a8b8125f00013769c3": "w.ludwig@web.de", "59b652c6e3567a0001d9bee2": "widanama@gmail.com", "59b65548faeeee0001d1e6fd": "johannes.raps@gmx.de", "59b650e55a8b5b0001311300": "oliver_adameck@gmx.de", "59f0680afc886300012d6629": "silvia.vassura@romagnafaentina.it", "59b65231faeeee0001d1e618": "speed_jassar@outlook.com", "59b654dbe782050001d67144": "lorei@stud.uni-heidelberg.de", "59b6548f5a8b5b0001311405": "markuslschneider@gmx.de", "59b6548afaeeee0001d1e6ca": "arnoguy@hotmail.com", "5a17174fd811d70001781d54": "damian.dabros@gmail.com", "59b6550afaeeee0001d1e6ea": "indianagigi@gmail.com", "59b655b85a8b5b0001311443": "Pieter.Nieuwkamer@outlook.com", "59b654cfe3567a0001d9bf6e": "f@f.com", "59b6533a5a8b5b00013113a4": "shawncabral20@gmail.com", "59b654a65a8b5b000131140d": "zumaia@gmail.com", "59b6532ce3567a0001d9befd": "carlo.pescetto@gmail.com", "59b6519fe3567a0001d9be98": "krzysgutowski@gmail.com", "59f60b09b8125f0001376aa0": "joel@longshotfreight.com", "59b655be0edf79000135db9f": "dfhjdfg@sdfgknfd.com", "59b651b90edf79000135da92": "kydavis@chcconsulting.com", "59e8ae6cb8125f0001376953": "Hurtig@T-Online.de", "59b652ed0edf79000135dadd": "manouti1988@gmail.com", "5a05527a4b19ef0001e96f41": "deadkjd131@gmail.com", "59b6517e0edf79000135da81": "gabriele.confortola@gmail.com", "59e7abbbb8125f0001376918": "louis.holli@gmail.com", "5a144b95ccadb80001e482ab": "contact@street-office.fr", "5a0b0c2d07a43a0001a8060e": "urh.marko@gmail.com", "59b654235a8b5b00013113e3": "vergiers@orange.fr", "59b6531c0edf79000135daed": "jonayreyes@gmail.com", "59b655965a8b5b000131143a": "saif.mirza@bookiply.com", "59b653170edf79000135daeb": "hanreev@gmail.com", "59b6512dfaeeee0001d1e5d8": "headers@gmail.com", "5a0b052464c3b40001536f26": "s.le-neindre@amiens-metropole.com", "59b65375faeeee0001d1e672": "azulhidalgo83@gmail.com", "59b65271faeeee0001d1e62f": "mats@lpa.net", "59b654575a8b5b00013113f3": "devops-gind@mines-albi.fr", "59ca22acd9724c0001d9d0fb": "marios.danakos@gmail.com", "59b653685a8b5b00013113b1": "jonathan@campusbot.de", "59b655b9faeeee0001d1e716": "julienroels@outlook.com", "59b653d0e3567a0001d9bf2c": "robert.kienberger@iovavum.com", "59b653d0e3567a0001d9bf2b": "leo.dewachter@gmail.com", "59b650ccdac3350001574f92": "sam@rndc.org", "59c3d5eb6070ca0001f62a1b": "maciej.bartminski@marketside.pl", "59b6552bfaeeee0001d1e6f5": "stefanos.zymis@savills.com", "59e0d88d09c47100010d13b7": "idalporto@mail.com", "59c5e86af1de77000168b7a1": "jmbille@hotmail.com", "59b654b5faeeee0001d1e6d6": "kleinerschabernack@yahoo.com.au", "59b655395a8b5b0001311429": "podolski3@web.de", "59b6526bfaeeee0001d1e62d": "vc@freeline-edv.de", "5a245c7c7b75940001a3dcc5": "mastro@live.de", "59b651b05a8b5b000131132f": "sandy.tulloch@smec.com", "59b653ffe3567a0001d9bf39": "ikar1988@outlook.com", "59b6517f0edf79000135da82": "martyn@tripleline.com", "5a1eaa20bbea300001f3472f": "info@alkoto.com", "59ea022fcdf3a400012b2591": "a.depanthou@planed.fr", "59b69bc7b857700001998c8c": "open-route-service@camille.utilise.des.services", "59b654cc5a8b5b0001311418": "michel.stuyts@gmail.com", "59b654e10edf79000135db78": "alainjfc@hku.hk", "59b652d65a8b5b0001311387": "dirk.broersen.external@atos.net", "59b6530ffaeeee0001d1e65b": "zwolin@gmail.com", "59b651aa5a8b5b000131132d": "andre.westendorf@opb.de", "59b6542de3567a0001d9bf47": "lukas@mschefczyk.de", "59b652ee0edf79000135dade": "fabio_lever@yahoo.com", "59b6534e0edf79000135db04": "samisnunu@yahoo.com", "59c2a34e7e6168000145da3a": "juzs@mail.ru", "5a031b4ef3b9100001206e74": "e.j.beeren@saxion.nl", "5a0db22e85ff890001891239": "drnick@smartmouthortho.com", "5a2fb93fb033230001aca511": "cartoalcala@gmail.com", "59b654e7e782050001d67149": "kbadinger@getcredentia.com", "59b654430edf79000135db53": "info@pabloobiol.com", "59b65160dac3350001574fac": "kosza.antal@gmail.com", "59b652cd5a8b5b0001311385": "cecile.lecoq@grouperougevif.fr", "59cad9e7bdfa50000167b746": "Ronmartin5671@gmail.com"}